Verilog_files/gfsk_modulator.v
/**
 * @module gfsk_mod
 * @brief Parameterized GFSK Modulator
 * @details Change the parameters at the top to scale the entire design.
 */
module gfsk_modulator #(
    parameter CLK_FREQ  = 400_000_000, // Internal high-speed clock rate
    parameter DATA_RATE = 20_000_000,  // Data rate (matches your sys_clk)
    parameter CARRIER   = 100_000_000, // Target carrier frequency
    parameter DEVIATION = 10_000_000   // Frequency shift for 0 vs 1
)(
    input  wire clk,         // High-speed clock from PLL
    input  wire rst_n,
    input  wire data_in,     // Data arrives at DATA_RATE speed
    output reg  modulated_out
);

    // --- Automatic Math (Computed at Synthesis) ---
    // SPS: Samples Per Symbol (e.g., 400MHz / 20Mbps = 20)
    localparam SPS = CLK_FREQ / DATA_RATE; 
    
    // NCO Tuning Words: (Target_Freq * 2^8) / CLK_FREQ
    localparam [7:0] M_CENTER = (CARRIER * 256) / CLK_FREQ;
    localparam [7:0] M_DEV    = (DEVIATION * 256) / CLK_FREQ;

    // --- Internal Registers ---
    reg [7:0] phase_acc;    // 8-bit Phase Accumulator
    reg [7:0] sample_cnt;   // Tracks samples per bit (0 to SPS-1)
    reg [2:0] shift_reg;    // History for Gaussian smoothing
    reg [7:0] m_current;    // Instantaneous frequency step

    // --- Gaussian Smoothing Logic ---
    // Divides the SPS window into 4 quadrants to ramp the frequency
    always @(*) begin
        case (shift_reg)
            3'b001: begin // Rising Transition
                if      (sample_cnt < (SPS/4))   m_current = M_CENTER - (M_DEV/2);
                else if (sample_cnt < (SPS/2))   m_current = M_CENTER;
                else if (sample_cnt < (3*SPS/4)) m_current = M_CENTER + (M_DEV/2);
                else                             m_current = M_CENTER + M_DEV;
            end
            3'b110: begin // Falling Transition
                if      (sample_cnt < (SPS/4))   m_current = M_CENTER + (M_DEV/2);
                else if (sample_cnt < (SPS/2))   m_current = M_CENTER;
                else if (sample_cnt < (3*SPS/4)) m_current = M_CENTER - (M_DEV/2);
                else                             m_current = M_CENTER - M_DEV;
            end
            3'b111:  m_current = M_CENTER + M_DEV; // Logic 1
            3'b000:  m_current = M_CENTER - M_DEV; // Logic 0
            default: m_current = M_CENTER;
        endcase
    end

    // --- Sequential Logic ---
    always @(posedge clk or negedge rst_n) begin
        if (!rst_n) begin
            phase_acc     <= 8'h00;
            sample_cnt    <= 8'h00;
            shift_reg     <= 3'b000;
            modulated_out <= 1'b0;
        end else begin
            // 1. Bit Timing
            if (sample_cnt >= (SPS - 1)) begin
                sample_cnt  <= 8'h00;
                shift_reg   <= {shift_reg[1:0], data_in};
            end else begin
                sample_cnt  <= sample_cnt + 8'd1;
            end

            // 2. NCO Phase Accumulation
            phase_acc <= phase_acc + m_current;

            // 3. Bitstream Output
            modulated_out <= phase_acc[7];
        end
    end
endmodule

Verilog_files/clock_gen_pll.v
`timescale 1ns / 1ps

module clock_gen_pll (
    input  wire clk_in,    // 20 MHz Input
    input  wire reset,     // Active High Reset
    output reg  clk_out,   // 400 MHz Output
    output reg  locked     // Status signal
);

    // Initial states
    initial begin
        clk_out = 0;
        locked = 0;
    end

    // PLL Locking Logic
    // In an ASIC, the analog loop takes time to stabilize.
    always @(posedge clk_in or posedge reset) begin
        if (reset) begin
            locked <= 0;
        end else begin
            // Simulate a lock time of 200ns
            #200 locked <= 1;
        end
    end

    // 400 MHz Clock Generation
    // Period = 2.5ns. Half-period = 1.25ns.
    always begin
        #1.25 clk_out = ~clk_out;
    end

endmodule

Verilog_files/tx_modulator_clocks.v
/**
 * @module tx_modulator_chain
 * @brief Wrapper for the transmission chain.
 * @details Change SYS_CLK_FREQ and PLL_MULT to scale everything.
 */
module tx_modulator_clocks #(
    parameter SYS_CLK_FREQ = 20_000_000, // CHANGE THIS to 10_000_000 if needed
    parameter PLL_MULT     = 20,         // Keep this at 20 for 20x SPS
    parameter CARRIER_FREQ = 100_000_000,
    parameter DEV_FREQ     = 10_000_000
)(
    input  wire ext_clk,
    input  wire rst_n,
    input  wire whitened_data_in,
    output wire rf_modulated_out
);

    // This calculates the internal frequency used for logic math
    localparam INT_CLK_FREQ = SYS_CLK_FREQ * PLL_MULT;

    wire clk_fast;
    wire locked;

    // --- PLL Instantiation ---
    // Note: You must ensure your PLL IP multiplier matches PLL_MULT
    clock_gen_pll i_pll (
        .clk_in(ext_clk),
        .clk_out(clk_fast),
        .reset(!rst_n),
        .locked(locked)
    );

    // --- GFSK Modulator Instance ---
    gfsk_modulator #(
        .CLK_FREQ(INT_CLK_FREQ),
        .DATA_RATE(SYS_CLK_FREQ), // Data rate tied to system clock
        .CARRIER(CARRIER_FREQ),
        .DEVIATION(DEV_FREQ)
    ) i_gfsk_modulator (
        .clk(clk_fast),
        .rst_n(rst_n && locked),
        .data_in(whitened_data_in),
        .modulated_out(rf_modulated_out)
    );

endmodule

Verilog_files/data_whitener.v
/**
This is the file that performs Data whitening on the PDU as well as the 24 bit CRC
Data whitening is an important process that helps in randomizing the data for better transmissison
Data whitening is done using LFSR wher the initial sequence is derived from the transmission channel index
*/

module data_whitener(
    clk,
    rst_n,
    lfsr_load,          // <-- Added this critical control signal
    enable,
    channel_index,
    data_in,
    whitened_data_out
);
   
   // --- Port Declarations ---
   input        clk;
   input        rst_n;
   input        lfsr_load;      // Pulse to load the channel value
   input        enable;         // Pulse to advance the LFSR
   input  [5:0] channel_index;
   input        data_in;
   output       whitened_data_out; // This is a 1-bit wire

   // --- Internal Signals ---
   reg  [6:0]    lfsr;           // The 7-bit LFSR register
   wire [6:0]    lfsr_seed;    // The 7-bit seed (from channel_index)
   wire [6:0]    lfsr_next;    // The next combinational value for the LFSR
   wire          lfsr_out_bit; // The LSB of the LFSR, used for whitening

   // --- Combinational Logic (The "Calculator") ---

   // 1. Create the 7-bit seed from the 6-bit channel index

   assign lfsr_seed = {channel_index, 1'b0};

   // 2. Define the LFSR's next-state logic (the polynomial)
   //    Polynomial: x^7 + x^4 + 1
   //    Taps are at lfsr[6] (for x^7) and lfsr[3] (for x^4)
   assign lfsr_next[6] = lfsr[5];
   assign lfsr_next[5] = lfsr[4];
   assign lfsr_next[4] = lfsr[3] ^ lfsr[6]; // Tap for x^4
   assign lfsr_next[3] = lfsr[2];
   assign lfsr_next[2] = lfsr[1];
   assign lfsr_next[1] = lfsr[0];
   assign lfsr_next[0] = lfsr[6];             // Tap for x^7

   // 3. Define the output bit (the LSB)
   assign lfsr_out_bit = lfsr[0];

   // 4. Define the final whitened output
   assign whitened_data_out = data_in ^ lfsr_out_bit;


   // --- Sequential Logic (The "Memory") ---
   // This block controls the LFSR register.
   // Load has priority over enable.
   always @(posedge clk or negedge rst_n) begin
        if (!rst_n) begin
            lfsr <= 7'b1111111; // Reset to a non-zero state
        end 
        else if (lfsr_load) begin
            // Load the LFSR with the channel seed value
            lfsr <= lfsr_seed; 
        end 
        else if (enable) begin
            // Advance the LFSR to the next state
            lfsr <= lfsr_next;
        end
   end

endmodule

Verilog_files/crc24_gen.v
/**
 * @module crc24_gen
 * @brief Implements the BLE 24-bit CRC
 */
module crc24_gen (
    clk,
    rst_n,
    enable,
    data_in,
    crc_out
);

    // --- Port Declarations ---
    input        clk;
    input        rst_n;
    input        enable;
    input        data_in;
    output [23:0] crc_out;

    // --- Internal Signals ---
    reg [23:0] crc_out;
    reg [23:0] crc_next;
    reg        feedback;

    localparam [23:0] CRC_INIT = 24'h555555;

    // --- Process 1: Combinational Logic (Calculator) ---
    // This logic implements the LSB-first CRC calculation.
 always @(*) begin
        
        // 1. Feedback bit is input XOR'd with the LSB
        feedback = data_in ^ crc_out[0]; 

        // 2. The register shifts RIGHT, with feedback XOR'd at the taps.
        // Polynomial: x^24 + x^10 + x^9 + x^6 + x^4 + x^3 + x + 1
        // Taps: 24, 10, 9, 6, 4, 3, 1, 0
        
        crc_next[0]  = crc_out[1]  ^ feedback; // Tap x^1
        crc_next[1]  = crc_out[2];
        crc_next[2]  = crc_out[3]  ^ feedback; // Tap x^3
        crc_next[3]  = crc_out[4]  ^ feedback; // Tap x^4
        crc_next[4]  = crc_out[5];
        crc_next[5]  = crc_out[6]  ^ feedback; // Tap x^6
        crc_next[6]  = crc_out[7];
        crc_next[7]  = crc_out[8];
        crc_next[8]  = crc_out[9]  ^ feedback; // Tap x^9
        crc_next[9]  = crc_out[10] ^ feedback; // Tap x^10
        crc_next[10] = crc_out[11];
        crc_next[11] = crc_out[12];
        crc_next[12] = crc_out[13];
        crc_next[13] = crc_out[14];
        crc_next[14] = crc_out[15];
        crc_next[15] = crc_out[16];
        crc_next[16] = crc_out[17];
        crc_next[17] = crc_out[18];
        crc_next[18] = crc_out[19];
        crc_next[19] = crc_out[20];
        crc_next[20] = crc_out[21];
        crc_next[21] = crc_out[22];
        crc_next[22] = crc_out[23];
        crc_next[23] = feedback;             // Tap x^24
    end
    // --- Process 2: Sequential Logic (Memory) ---
    always @(posedge clk or negedge rst_n) begin
        if (!rst_n) begin
            crc_out <= CRC_INIT;
        end else if (enable) begin
            crc_out <= crc_next;
        end
    end

endmodule

Verilog_files/packet_framer.v
/**
 * @module packet_framer
 * @brief ASIC-ready BLE Packet Framer with Dynamic Length Tracking.
 */
module packet_framer #(
    parameter [31:0] ACCESS_ADDR = 32'h8E89BED6, // Advertising Access Address
    parameter [5:0]  CHANNEL_IDX = 6'd37         // Default Adv Channel
)(
    input  wire        clk,               // 20MHz System Clock
    input  wire        rst_n,
    input  wire        start_tx,          // Pulse to start packet
    input  wire [7:0]  tx_data_in,        // From CPU/DMA
    input  wire        tx_valid_in,       // Data valid handshake
    input  wire [23:0] crc_in,            // From CRC Engine
    
    output reg         tx_ready_out,      // Handshake to CPU
    output reg         irq_tx_done,       // Interrupt: Packet complete
    output reg         crc_enable,        // Enable CRC block
    output reg         whitener_enable,   // Enable Whitener block
    output wire [5:0]  channel_index_out, // For Whitener seed
    output reg         serial_data_out    // To Whitener/Modulator
);

    // --- State Encoding (7 States) ---
    localparam IDLE         = 3'd0,
               PREAMBLE     = 3'd1,
               ADDR         = 3'd2,
               HEADER       = 3'd3,
               PAYLOAD      = 3'd4,
               CRC_SUM      = 3'd5,
               DONE         = 3'd6;

    reg [2:0] state;
    reg [5:0] bit_cnt;       // Counts bits within fields
    reg [7:0] byte_cnt;      // Counts total bytes in PDU
    reg [7:0] packet_length; // Captured from 2nd byte of PDU
    reg [7:0] shift_reg;     // Serialization buffer

    assign channel_index_out = CHANNEL_IDX;

    // --- FSM Logic ---
    always @(posedge clk or negedge rst_n) begin
        if (!rst_n) begin
            state           <= IDLE;
            bit_cnt         <= 0;
            byte_cnt        <= 0;
            packet_length   <= 0;
            tx_ready_out    <= 0;
            irq_tx_done     <= 0;
            crc_enable      <= 0;
            whitener_enable <= 0;
            serial_data_out <= 0;
            shift_reg       <= 0;
        end else begin
            case (state)
                
                // 1. IDLE: Wait for start command
                IDLE: begin
                    irq_tx_done <= 0;
                    if (start_tx) begin
                        state   <= PREAMBLE;
                        bit_cnt <= 0;
                    end
                end

                // 2. PREAMBLE: Send fixed 8'hAA (LSB first: 01010101)
                PREAMBLE: begin
                    serial_data_out <= bit_cnt[0]; 
                    if (bit_cnt == 7) begin
                        state   <= ADDR;
                        bit_cnt <= 0;
                    end else bit_cnt <= bit_cnt + 1'b1;
                end

                // 3. ACCESS_ADDR: Send 32-bit address (No Whitening/CRC)
                ADDR: begin
                    serial_data_out <= ACCESS_ADDR[bit_cnt[4:0]];
                    if (bit_cnt == 31) begin
                        state        <= HEADER;
                        bit_cnt      <= 0;
                        tx_ready_out <= 1; // Request first byte of PDU
                    end else bit_cnt <= bit_cnt + 1'b1;
                end

                // 4. HEADER: Send 16-bit PDU Header (Whitening & CRC Start)
                HEADER: begin
                    whitener_enable <= 1;
                    crc_enable      <= 1;

                    if (tx_valid_in && tx_ready_out) begin
                        shift_reg    <= tx_data_in;
                        tx_ready_out <= 0; // Buffer full
                        // Capture length byte (2nd byte of Header)
                        if (byte_cnt == 1) packet_length <= tx_data_in;
                    end

                    serial_data_out <= shift_reg[bit_cnt[2:0]];
                    
                    if (bit_cnt == 7) begin
                        bit_cnt <= 0;
                        tx_ready_out <= 1;
                        if (byte_cnt == 1) begin
                            state <= PAYLOAD;
                            byte_cnt <= 0; // Reset for payload count
                        end else byte_cnt <= byte_cnt + 1'b1;
                    end else bit_cnt <= bit_cnt + 1'b1;
                end

                // 5. PAYLOAD: Send actual data based on captured packet_length
                PAYLOAD: begin
                    if (tx_valid_in && tx_ready_out) begin
                        shift_reg    <= tx_data_in;
                        tx_ready_out <= 0;
                    end

                    serial_data_out <= shift_reg[bit_cnt[2:0]];

                    if (bit_cnt == 7) begin
                        bit_cnt <= 0;
                        tx_ready_out <= 1;
                        // End of payload detection
                        if (byte_cnt == (packet_length - 1)) begin
                            state      <= CRC_SUM;
                            crc_enable <= 0; // Freeze CRC engine
                        end else byte_cnt <= byte_cnt + 1'b1;
                    end else bit_cnt <= bit_cnt + 1'b1;
                end

                // 6. CRC_SUM: Send 24-bit calculated CRC (Whitened)
                CRC_SUM: begin
                    tx_ready_out    <= 0;
                    serial_data_out <= crc_in[bit_cnt[4:0]];
                    if (bit_cnt == 23) begin
                        state           <= DONE;
                        whitener_enable <= 0;
                    end else bit_cnt    <= bit_cnt + 1'b1;
                end

                // 7. DONE: Cleanup and notify CPU
                DONE: begin
                    irq_tx_done     <= 1;
                    serial_data_out <= 0;
                    state           <= IDLE;
                end

                default: state <= IDLE;
            endcase
        end
    end
endmodule

Verilog_files/ble_tx_top.v
/**
 * @module ble_tx_top
 * @brief Top-level integration for the BLE Baseband Transmitter.
 */
module ble_tx_top (
    input  wire        ext_clk,     // 20MHz External Clock
    input  wire        rst_n,
    input  wire        start_tx,    // Pulse to begin packet
    input  wire [7:0]  tx_data_in,  // From CPU/DMA
    input  wire        tx_valid_in, // Data valid handshake
    
    output wire        tx_ready_out, // Handshake to CPU
    output wire        irq_tx_done,  // Interrupt: Packet complete
    output wire        rf_out        // Final GFSK Modulated Signal
);

    // --- Internal Interconnects ---
    wire [5:0]  channel_idx;
    wire [23:0] crc_val;
    wire        framer_serial_out;
    wire        crc_en;
    wire        white_en;
    wire        whitened_stream;

    // 1. Packet Framer (The Conductor)
    packet_framer i_framer (
        .clk(ext_clk),
        .rst_n(rst_n),
        .start_tx(start_tx),
        .tx_data_in(tx_data_in),
        .tx_valid_in(tx_valid_in),
        .crc_in(crc_val),
        .tx_ready_out(tx_ready_out),
        .irq_tx_done(irq_tx_done),
        .crc_enable(crc_en),
        .whitener_enable(white_en),
        .channel_index_out(channel_idx),
        .serial_data_out(framer_serial_out)
    );

    // 2. CRC Engine (The Guard)
    crc24_gen i_crc (
        .clk(ext_clk),
        .rst_n(rst_n),
        .enable(crc_en),
        .data_in(framer_serial_out),
        .crc_out(crc_val)
    );

    // 3. Data Whitener (The Scrambler)
    data_whitener i_whitener (
        .clk(ext_clk),
        .rst_n(rst_n),
        .lfsr_load(start_tx), // Seed LFSR when packet starts
        .enable(white_en),    // Only advance LFSR when in Header/Payload/CRC states
        .channel_index(channel_idx),
        .data_in(framer_serial_out),
        .whitened_data_out(whitened_stream)
    );

    // 4. Modulator Chain (The Radio Interface)
    // Ties the 20MHz whitened stream to the 400MHz GFSK engine
    tx_modulator_clocks i_modulator_chain (
        .ext_clk(ext_clk),
        .rst_n(rst_n),
        .whitened_data_in(whitened_stream),
        .rf_modulated_out(rf_out)
    );

endmodule

Testbenches/ble_tx_system_tb.v
`timescale 1ns / 1ps

/**
 * @module ble_tx_system_tb
 * @brief Interactive Profiling Testbench using SystemVerilog
 */
module ble_tx_system_tb;

    // --- Signals ---
    reg         ext_clk;
    reg         rst_n;
    reg         start_tx;
    reg  [7:0]  tx_data_in;
    reg         tx_valid_in;

    wire        tx_ready_out;
    wire        irq_tx_done;
    wire        rf_out;

    // --- Instantiate the Top-Level System ---
    ble_tx_top uut (
        .ext_clk(ext_clk),
        .rst_n(rst_n),
        .start_tx(start_tx),
        .tx_data_in(tx_data_in),
        .tx_valid_in(tx_valid_in),
        .tx_ready_out(tx_ready_out),
        .irq_tx_done(irq_tx_done),
        .rf_out(rf_out)
    );

    // --- Clock Generation ---
    initial ext_clk = 0;
    always #25 ext_clk = ~ext_clk; // 20MHz (50ns period)

    // --- Statistics Tracking Variables ---
    integer total_cycles = 0;
    integer state_cycles [0:6]; // Array to count cycles for each of the 7 states
    
    string user_payload = "TEST"; // Default payload
    integer payload_length;
    integer i;

    // --- Cycle Counting Block (The Snooper) ---
    // This runs in the background and watches the internal FSM state
    always @(posedge ext_clk) begin
        if (rst_n) begin
            total_cycles++;
            // Hierarchical access: peeking directly into the framer's state register
            state_cycles[uut.i_framer.state]++; 
        end
    end

    // --- Main Test Procedure ---
    initial begin
        $dumpfile("ble_system_full.vcd");
        $dumpvars(0, ble_tx_system_tb);

        // 0. Initialize Counters
        for (i = 0; i < 7; i++) state_cycles[i] = 0;

        // 1. Fetch Terminal Input
        // If the user runs the sim with +MSG="Hello", it overrides the default
        if ($value$plusargs("MSG=%s", user_payload)) begin
            $display("-----------------------------------------");
            $display(">> Terminal Input Detected: '%s'", user_payload);
        end else begin
            $display("-----------------------------------------");
            $display(">> No input detected. Using default: '%s'", user_payload);
        end
        
        payload_length = user_payload.len();
        $display(">> Payload Size: %0d bytes", payload_length);
        $display("-----------------------------------------");

        // 2. System Reset
        rst_n = 0;
        start_tx = 0;
        tx_data_in = 0;
        tx_valid_in = 0;
        #200 rst_n = 1;
        #100;

        // 3. Initiate Transmission
        @(posedge ext_clk);
        start_tx = 1;
        @(posedge ext_clk);
        start_tx = 0;

        // 4. Feed the Header
        feed_byte(8'h00); // ADV_IND
        feed_byte(payload_length[7:0]); // Dynamic Length Byte

        // 5. Feed the Payload Loop (ASCII Conversion)
        for (i = 0; i < payload_length; i++) begin
            // Extract single character from string and cast to byte
            feed_byte(user_payload[i]); 
        end

        // 6. Wait for Hardware to Finish
        wait(irq_tx_done);
        #500; 

        // 7. Print Final Profiling Statistics
        print_statistics();
        $finish;
    end

    // --- Task: CPU/DMA Handshake ---
    task feed_byte(input [7:0] data);
        begin
            while (!tx_ready_out) @(posedge ext_clk);
            tx_data_in  = data;
            tx_valid_in = 1;
            
            @(posedge ext_clk);
            while (tx_ready_out) @(posedge ext_clk);
            tx_valid_in = 0;
        end
    endtask

    // --- Task: Print Profiling Report ---
    task print_statistics;
        begin
            $display("\n=========================================");
            $display("       BLE TX HARDWARE PROFILING         ");
            $display("=========================================");
            $display(" Payload Sent : '%s'", user_payload);
            $display(" Payload Size : %0d Bytes (%0d bits)", payload_length, payload_length*8);
            $display(" Total Time   : %0d ns", $time);
            $display(" Total Cycles : %0d", total_cycles);
            $display("-----------------------------------------");
            $display(" Cycles Spent Per FSM Stage:");
            $display("   [0] IDLE     : %0d", state_cycles[0]);
            $display("   [1] PREAMBLE : %0d (Expected ~8)", state_cycles[1]);
            $display("   [2] ADDR     : %0d (Expected ~32)", state_cycles[2]);
            $display("   [3] HEADER   : %0d (Expected ~16)", state_cycles[3]);
            $display("   [4] PAYLOAD  : %0d (Expected ~%0d)", state_cycles[4], payload_length*8);
            $display("   [5] CRC      : %0d (Expected ~24)", state_cycles[5]);
            $display("   [6] DONE     : %0d", state_cycles[6]);
            $display("=========================================\n");
        end
    endtask

endmodule

Waveforms/ble_system_full.vcd
$date
	Tue Mar 31 21:52:12 2026
$end
$version
	Icarus Verilog
$end
$timescale
	1ps
$end
$scope module ble_tx_system_tb $end
$var wire 1 ! tx_ready_out $end
$var wire 1 " rf_out $end
$var wire 1 # irq_tx_done $end
$var reg 1 $ ext_clk $end
$var reg 1 % rst_n $end
$var reg 1 & start_tx $end
$var reg 8 ' tx_data_in [7:0] $end
$var reg 1 ( tx_valid_in $end
$var integer 32 ) i [31:0] $end
$var integer 32 * payload_length [31:0] $end
$var integer 32 + total_cycles [31:0] $end
$scope module uut $end
$var wire 6 , channel_idx [5:0] $end
$var wire 1 $ ext_clk $end
$var wire 1 % rst_n $end
$var wire 1 & start_tx $end
$var wire 8 - tx_data_in [7:0] $end
$var wire 1 ( tx_valid_in $end
$var wire 1 . whitened_stream $end
$var wire 1 / white_en $end
$var wire 1 ! tx_ready_out $end
$var wire 1 " rf_out $end
$var wire 1 # irq_tx_done $end
$var wire 1 0 framer_serial_out $end
$var wire 24 1 crc_val [23:0] $end
$var wire 1 2 crc_en $end
$scope module i_crc $end
$var wire 1 $ clk $end
$var wire 1 % rst_n $end
$var wire 1 2 enable $end
$var wire 1 0 data_in $end
$var reg 24 3 crc_next [23:0] $end
$var reg 24 4 crc_out [23:0] $end
$var reg 1 5 feedback $end
$upscope $end
$scope module i_framer $end
$var wire 6 6 channel_index_out [5:0] $end
$var wire 1 $ clk $end
$var wire 24 7 crc_in [23:0] $end
$var wire 1 % rst_n $end
$var wire 1 & start_tx $end
$var wire 8 8 tx_data_in [7:0] $end
$var wire 1 ( tx_valid_in $end
$var reg 6 9 bit_cnt [5:0] $end
$var reg 8 : byte_cnt [7:0] $end
$var reg 1 2 crc_enable $end
$var reg 1 # irq_tx_done $end
$var reg 8 ; packet_length [7:0] $end
$var reg 1 0 serial_data_out $end
$var reg 8 < shift_reg [7:0] $end
$var reg 3 = state [2:0] $end
$var reg 1 ! tx_ready_out $end
$var reg 1 / whitener_enable $end
$upscope $end
$scope module i_modulator_chain $end
$var wire 1 $ ext_clk $end
$var wire 1 % rst_n $end
$var wire 1 . whitened_data_in $end
$var wire 1 " rf_modulated_out $end
$var wire 1 > locked $end
$var wire 1 ? clk_fast $end
$scope module i_gfsk_modulator $end
$var wire 1 @ rst_n $end
$var wire 1 . data_in $end
$var wire 1 ? clk $end
$var reg 8 A m_current [7:0] $end
$var reg 1 " modulated_out $end
$var reg 8 B phase_acc [7:0] $end
$var reg 8 C sample_cnt [7:0] $end
$var reg 3 D shift_reg [2:0] $end
$upscope $end
$scope module i_pll $end
$var wire 1 $ clk_in $end
$var wire 1 E reset $end
$var reg 1 ? clk_out $end
$var reg 1 > locked $end
$upscope $end
$upscope $end
$scope module i_whitener $end
$var wire 6 F channel_index [5:0] $end
$var wire 1 $ clk $end
$var wire 1 0 data_in $end
$var wire 1 / enable $end
$var wire 1 & lfsr_load $end
$var wire 7 G lfsr_seed [6:0] $end
$var wire 1 % rst_n $end
$var wire 1 . whitened_data_out $end
$var wire 1 H lfsr_out_bit $end
$var wire 7 I lfsr_next [6:0] $end
$var reg 7 J lfsr [6:0] $end
$upscope $end
$upscope $end
$scope task feed_byte $end
$var reg 8 K data [7:0] $end
$upscope $end
$scope task print_statistics $end
$upscope $end
$upscope $end
$enddefinitions $end
#0
$dumpvars
bx K
b1111111 J
b1101111 I
1H
b1001010 G
b100101 F
1E
b0 D
b0 C
b0 B
b111010 A
0@
0?
0>
b0 =
b0 <
b0 ;
b0 :
b0 9
b0 8
b10101010101010101010101 7
b100101 6
15
b10101010101010101010101 4
b101010101010100110000111 3
02
b10101010101010101010101 1
00
0/
1.
b0 -
b100101 ,
b0 +
b1 *
b111 )
0(
b0 '
0&
0%
0$
0#
0"
0!
$end
#1250
1?
#2500
0?
#3750
1?
#5000
0?
#6250
1?
#7500
0?
#8750
1?
#10000
0?
#11250
1?
#12500
0?
#13750
1?
#15000
0?
#16250
1?
#17500
0?
#18750
1?
#20000
0?
#21250
1?
#22500
0?
#23750
1?
#25000
0?
1$
#26250
1?
#27500
0?
#28750
1?
#30000
0?
#31250
1?
#32500
0?
#33750
1?
#35000
0?
#36250
1?
#37500
0?
#38750
1?
#40000
0?
#41250
1?
#42500
0?
#43750
1?
#45000
0?
#46250
1?
#47500
0?
#48750
1?
#50000
0?
0$
#51250
1?
#52500
0?
#53750
1?
#55000
0?
#56250
1?
#57500
0?
#58750
1?
#60000
0?
#61250
1?
#62500
0?
#63750
1?
#65000
0?
#66250
1?
#67500
0?
#68750
1?
#70000
0?
#71250
1?
#72500
0?
#73750
1?
#75000
0?
1$
#76250
1?
#77500
0?
#78750
1?
#80000
0?
#81250
1?
#82500
0?
#83750
1?
#85000
0?
#86250
1?
#87500
0?
#88750
1?
#90000
0?
#91250
1?
#92500
0?
#93750
1?
#95000
0?
#96250
1?
#97500
0?
#98750
1?
#100000
0?
0$
#101250
1?
#102500
0?
#103750
1?
#105000
0?
#106250
1?
#107500
0?
#108750
1?
#110000
0?
#111250
1?
#112500
0?
#113750
1?
#115000
0?
#116250
1?
#117500
0?
#118750
1?
#120000
0?
#121250
1?
#122500
0?
#123750
1?
#125000
0?
1$
#126250
1?
#127500
0?
#128750
1?
#130000
0?
#131250
1?
#132500
0?
#133750
1?
#135000
0?
#136250
1?
#137500
0?
#138750
1?
#140000
0?
#141250
1?
#142500
0?
#143750
1?
#145000
0?
#146250
1?
#147500
0?
#148750
1?
#150000
0?
0$
#151250
1?
#152500
0?
#153750
1?
#155000
0?
#156250
1?
#157500
0?
#158750
1?
#160000
0?
#161250
1?
#162500
0?
#163750
1?
#165000
0?
#166250
1?
#167500
0?
#168750
1?
#170000
0?
#171250
1?
#172500
0?
#173750
1?
#175000
0?
1$
#176250
1?
#177500
0?
#178750
1?
#180000
0?
#181250
1?
#182500
0?
#183750
1?
#185000
0?
#186250
1?
#187500
0?
#188750
1?
#190000
0?
#191250
1?
#192500
0?
#193750
1?
#195000
0?
#196250
1?
#197500
0?
#198750
1?
#200000
0?
0$
0E
1%
#201250
1?
#202500
0?
#203750
1?
#205000
0?
#206250
1?
#207500
0?
#208750
1?
#210000
0?
#211250
1?
#212500
0?
#213750
1?
#215000
0?
#216250
1?
#217500
0?
#218750
1?
#220000
0?
#221250
1?
#222500
0?
#223750
1?
#225000
b1 +
0?
1$
#226250
1?
#227500
0?
#228750
1?
#230000
0?
#231250
1?
#232500
0?
#233750
1?
#235000
0?
#236250
1?
#237500
0?
#238750
1?
#240000
0?
#241250
1?
#242500
0?
#243750
1?
#245000
0?
#246250
1?
#247500
0?
#248750
1?
#250000
0?
0$
#251250
1?
#252500
0?
#253750
1?
#255000
0?
#256250
1?
#257500
0?
#258750
1?
#260000
0?
#261250
1?
#262500
0?
#263750
1?
#265000
0?
#266250
1?
#267500
0?
#268750
1?
#270000
0?
#271250
1?
#272500
0?
#273750
1?
#275000
b10 +
0?
1$
#276250
1?
#277500
0?
#278750
1?
#280000
0?
#281250
1?
#282500
0?
#283750
1?
#285000
0?
#286250
1?
#287500
0?
#288750
1?
#290000
0?
#291250
1?
#292500
0?
#293750
1?
#295000
0?
#296250
1?
#297500
0?
#298750
1?
#300000
0?
0$
#301250
1?
#302500
0?
#303750
1?
#305000
0?
#306250
1?
#307500
0?
#308750
1?
#310000
0?
#311250
1?
#312500
0?
#313750
1?
#315000
0?
#316250
1?
#317500
0?
#318750
1?
#320000
0?
#321250
1?
#322500
0?
#323750
1?
#325000
0.
b101 I
0H
b1001010 J
b1 =
b11 +
1&
0?
1$
#326250
1?
#327500
0?
#328750
1?
#330000
0?
#331250
1?
#332500
0?
#333750
1?
#335000
0?
#336250
1?
#337500
0?
#338750
1?
#340000
0?
#341250
1?
#342500
0?
#343750
1?
#345000
0?
#346250
1?
#347500
0?
#348750
1?
#350000
0?
0$
#351250
1?
#352500
0?
#353750
1?
#355000
0?
#356250
1?
#357500
0?
#358750
1?
#360000
0?
#361250
1?
#362500
0?
#363750
1?
#365000
0?
#366250
1?
#367500
0?
#368750
1?
#370000
0?
#371250
1?
#372500
0?
#373750
1?
#375000
b1 9
b0 K
0&
b100 +
0?
1$
#376250
1?
#377500
0?
#378750
1?
#380000
0?
#381250
1?
#382500
0?
#383750
1?
#385000
0?
#386250
1?
#387500
0?
#388750
1?
#390000
0?
#391250
1?
#392500
0?
#393750
1?
#395000
0?
#396250
1?
#397500
0?
#398750
1?
#400000
0?
0$
#401250
1?
#402500
0?
#403750
1?
#405000
0?
#406250
1?
#407500
0?
#408750
1?
#410000
0?
#411250
1?
#412500
0?
#413750
1?
#415000
0?
#416250
1?
#417500
0?
#418750
1?
#420000
0?
#421250
1?
#422500
0?
#423750
1?
#425000
1.
b1010101010101010101010 3
05
1@
b10 9
10
1>
b101 +
0?
1$
#426250
b111010 B
b1 C
1?
#427500
0?
#428750
b1110100 B
b10 C
1?
#430000
0?
#431250
b10101110 B
b11 C
1?
#432500
0?
#433750
1"
b11101000 B
b100 C
1?
#435000
0?
#436250
b100010 B
b101 C
1?
#437500
0?
#438750
0"
b1011100 B
b110 C
1?
#440000
0?
#441250
b10010110 B
b111 C
1?
#442500
0?
#443750
1"
b11010000 B
b1000 C
1?
#445000
0?
#446250
b1010 B
b1001 C
1?
#447500
0?
#448750
0"
b1000100 B
b1010 C
1?
#450000
0?
0$
#451250
b1111110 B
b1011 C
1?
#452500
0?
#453750
b10111000 B
b1100 C
1?
#455000
0?
#456250
1"
b11110010 B
b1101 C
1?
#457500
0?
#458750
b101100 B
b1110 C
1?
#460000
0?
#461250
0"
b1100110 B
b1111 C
1?
#462500
0?
#463750
b10100000 B
b10000 C
1?
#465000
0?
#466250
1"
b11011010 B
b10001 C
1?
#467500
0?
#468750
b10100 B
b10010 C
1?
#470000
0?
#471250
0"
b1001110 B
b10011 C
1?
#472500
0?
#473750
b111101 A
b10001000 B
b1 D
b0 C
1?
#475000
0.
b101010101010100110000111 3
15
b11 9
00
b110 +
0?
1$
#476250
1"
b11000101 B
b1 C
1?
#477500
0?
#478750
b10 B
b10 C
1?
#480000
0?
#481250
0"
b111111 B
b11 C
1?
#482500
0?
#483750
b1111100 B
b100 C
1?
#485000
0?
#486250
b1000000 A
b10111001 B
b101 C
1?
#487500
0?
#488750
1"
b11111001 B
b110 C
1?
#490000
0?
#491250
b111001 B
b111 C
1?
#492500
0?
#493750
0"
b1111001 B
b1000 C
1?
#495000
0?
#496250
b10111001 B
b1001 C
1?
