Verilog_files/data_whitener.v
/**
This is the file that performs Data whitening on the PDU as well as the 24 bit CRC
Data whitening is an important process that helps in randomizing the data for better transmissison
Data whitening is done using LFSR wher the initial sequence is derived from the transmission channel index
*/

module data_whitener(
    clk,
    rst_n,
    lfsr_load,          // <-- Added this critical control signal
    enable,
    channel_index,
    data_in,
    whitened_data_out
);
   
   // --- Port Declarations ---
   input        clk;
   input        rst_n;
   input        lfsr_load;      // Pulse to load the channel value
   input        enable;         // Pulse to advance the LFSR
   input  [5:0] channel_index;
   input        data_in;
   output       whitened_data_out; // This is a 1-bit wire

   // --- Internal Signals ---
   reg  [6:0]    lfsr;           // The 7-bit LFSR register
   wire [6:0]    lfsr_seed;    // The 7-bit seed (from channel_index)
   wire [6:0]    lfsr_next;    // The next combinational value for the LFSR
   wire          lfsr_out_bit; // The LSB of the LFSR, used for whitening

   // --- Combinational Logic (The "Calculator") ---

   // 1. Create the 7-bit seed from the 6-bit channel index

   assign lfsr_seed = {channel_index, 1'b0};

   // 2. Define the LFSR's next-state logic (the polynomial)
   //    Polynomial: x^7 + x^4 + 1
   //    Taps are at lfsr[6] (for x^7) and lfsr[3] (for x^4)
   assign lfsr_next[6] = lfsr[5];
   assign lfsr_next[5] = lfsr[4];
   assign lfsr_next[4] = lfsr[3] ^ lfsr[6]; // Tap for x^4
   assign lfsr_next[3] = lfsr[2];
   assign lfsr_next[2] = lfsr[1];
   assign lfsr_next[1] = lfsr[0];
   assign lfsr_next[0] = lfsr[6];             // Tap for x^7

   // 3. Define the output bit (the LSB)
   assign lfsr_out_bit = lfsr[0];

   // 4. Define the final whitened output
   assign whitened_data_out = data_in ^ lfsr_out_bit;


   // --- Sequential Logic (The "Memory") ---
   // This block controls the LFSR register.
   // Load has priority over enable.
   always @(posedge clk or negedge rst_n) begin
        if (!rst_n) begin
            lfsr <= 7'b1111111; // Reset to a non-zero state
        end 
        else if (lfsr_load) begin
            // Load the LFSR with the channel seed value
            lfsr <= lfsr_seed; 
        end 
        else if (enable) begin
            // Advance the LFSR to the next state
            lfsr <= lfsr_next;
        end
   end

endmodule

Verilog_files/data_dewhitener.v
/**
 * @module data_dewhitener
 * @brief Inverse of Data Whitener - Descrambles whitened BLE data
 * @details Uses identical LFSR to the whitener to recover original bit stream
 */
module data_dewhitener(
    clk,
    rst_n,
    lfsr_load,          // Pulse to load the channel value
    enable,
    channel_index,
    data_in,            // Whitened data (from demodulator)
    dewhitened_data_out // Original data (descrambled)
);
   
    // --- Port Declarations ---
    input        clk;
    input        rst_n;
    input        lfsr_load;       // Pulse to load the channel value
    input        enable;          // Pulse to advance the LFSR
    input  [5:0] channel_index;
    input        data_in;         // Whitened data input
    output       dewhitened_data_out; // Dewhitened output (1-bit)

    // --- Internal Signals ---
    reg  [6:0]   lfsr;            // The 7-bit LFSR register
    wire [6:0]   lfsr_seed;       // The 7-bit seed (from channel_index)
    wire [6:0]   lfsr_next;       // The next combinational value for the LFSR
    wire         lfsr_out_bit;    // The LSB of the LFSR, used for dewhitening

    // --- Combinational Logic (The "Calculator") ---

    // 1. Create the 7-bit seed from the 6-bit channel index
    assign lfsr_seed = {channel_index, 1'b0};

    // 2. Define the LFSR's next-state logic (the polynomial)
    //    Polynomial: x^7 + x^4 + 1
    //    Taps are at lfsr[6] (for x^7) and lfsr[3] (for x^4)
    assign lfsr_next[6] = lfsr[5];
    assign lfsr_next[5] = lfsr[4];
    assign lfsr_next[4] = lfsr[3] ^ lfsr[6]; // Tap for x^4
    assign lfsr_next[3] = lfsr[2];
    assign lfsr_next[2] = lfsr[1];
    assign lfsr_next[1] = lfsr[0];
    assign lfsr_next[0] = lfsr[6];             // Tap for x^7

    // 3. Define the output bit (the LSB) - same as whitener
    assign lfsr_out_bit = lfsr[0];

    // 4. Define the final dewhitened output (XOR recovers original data)
    assign dewhitened_data_out = data_in ^ lfsr_out_bit;


    // --- Sequential Logic (The "Memory") ---
    // This block controls the LFSR register.
    // Load has priority over enable.
    always @(posedge clk or negedge rst_n) begin
        if (!rst_n) begin
            lfsr <= 7'b1111111; // Reset to a non-zero state
        end 
        else if (lfsr_load) begin
            // Load the LFSR with the channel seed value
            lfsr <= lfsr_seed; 
        end 
        else if (enable) begin
            // Advance the LFSR to the next state
            lfsr <= lfsr_next;
        end
    end

endmodule

Testbenches/data_dewhitener_tb.v
`timescale 1ns / 1ps

module data_dewhitener_tb;

    // --- Inputs ---
    reg        clk;
    reg        rst_n;
    reg        lfsr_load;
    reg        enable;
    reg [5:0]  channel_index;
    reg        data_in;

    // --- Outputs ---
    wire       dewhitened_data_out;
    wire       whitened_data_ref;

    // --- The "Golden Model" (Shadow LFSR) ---
    reg [6:0]  tb_lfsr;
    reg        expected_dewhitened;

    // --- Test Variables ---
    reg [39:0] test_pattern;
    integer i;

    // --- Instantiate the Dewhitener ---
    data_dewhitener uut_dewhitener (
        .clk(clk),
        .rst_n(rst_n),
        .lfsr_load(lfsr_load),
        .enable(enable),
        .channel_index(channel_index),
        .data_in(data_in),
        .dewhitened_data_out(dewhitened_data_out)
    );

    // --- Instantiate a whitener for loopback comparison ---
    data_whitener uut_whitener (
        .clk(clk),
        .rst_n(rst_n),
        .lfsr_load(lfsr_load),
        .enable(enable),
        .channel_index(channel_index),
        .data_in(dewhitened_data_out), 
        .whitened_data_out(whitened_data_ref)
    );

    // --- Clock Generator (20MHz -> 50ns period) ---
    parameter CLK_PERIOD = 50;
    always begin
        clk = 0; #(CLK_PERIOD / 2);
        clk = 1; #(CLK_PERIOD / 2);
    end

    // =========================================================
    // SMART TASKS FOR AUTOMATED TESTING
    // =========================================================

    // Task 1: Load Channel into Hardware and Shadow LFSR
    task load_channel(input [5:0] ch);
        begin
            @(negedge clk);
            channel_index = ch;
            lfsr_load = 1;
            
            // Seed the testbench's shadow LFSR identical to the hardware
            tb_lfsr = {ch, 1'b0}; 
            
            @(posedge clk);
            #1 lfsr_load = 0;
            $display("\n>>> Loaded Channel Index: %0d (Seed: %b) <<<", ch, tb_lfsr);
        end
    endtask

    // Task 2: Feed data, auto-calculate, and verify
    task feed_and_check(input reg test_bit);
        begin
            @(negedge clk);
            data_in = test_bit;
            enable  = 1;

            // Wait 1ns for the hardware's combinational XOR to settle
            #1; 

            // 1. Calculate the expected answer using the CURRENT LFSR state
            expected_dewhitened = test_bit ^ tb_lfsr[0];

            // 2. Automated Comparison (BEFORE the clock edge shifts the hardware)
            if ((dewhitened_data_out === expected_dewhitened) && (whitened_data_ref === test_bit)) begin
                $display("[PASS] In: %b | Dewhitened: %b (Expected: %b) | Re-Whitened Loopback: %b", 
                         test_bit, dewhitened_data_out, expected_dewhitened, whitened_data_ref);
            end else begin
                $display("[ERROR] In: %b | Dewhitened: %b (Expected: %b) | Re-Whitened Loopback: %b", 
                         test_bit, dewhitened_data_out, expected_dewhitened, whitened_data_ref);
            end

            // 3. Now wait for the rising edge that shifts the hardware LFSR...
            @(posedge clk);
            
            // ...and shift our testbench LFSR to match it!
            tb_lfsr = {tb_lfsr[5], tb_lfsr[4], tb_lfsr[3] ^ tb_lfsr[6], tb_lfsr[2], tb_lfsr[1], tb_lfsr[0], tb_lfsr[6]};
        end
    endtask

    // =========================================================
    // MAIN TEST SEQUENCE
    // =========================================================
    initial begin
        $dumpfile("dewhitener_test.vcd");
        $dumpvars(0, data_dewhitener_tb);

        $display("=== Starting Automated Data Dewhitener Verification ===");
        rst_n = 0;
        lfsr_load = 0;
        enable = 0;
        channel_index = 0;
        data_in = 0;
        #(CLK_PERIOD * 2);
        rst_n = 1;
        #(CLK_PERIOD);

        // --- Test 1: Random Pattern ---
        load_channel(6'd37); 
        test_pattern = 40'b0011010110001101;
        for (i = 0; i < 16; i = i + 1) begin
            feed_and_check(test_pattern[i]);
        end
        enable = 0; #(CLK_PERIOD * 3);

        // --- Test 2: Stream of Zeros ---
        load_channel(6'd21); // Channel 21
        for (i = 0; i < 10; i = i + 1) begin
            feed_and_check(1'b0);
        end
        enable = 0; #(CLK_PERIOD * 3);

        // --- Test 3: Stream of Ones ---
        load_channel(6'd51); // Channel 51
        for (i = 0; i < 10; i = i + 1) begin
            feed_and_check(1'b1);
        end
        enable = 0; #(CLK_PERIOD * 3);

        $display("\n=== Verification Complete ===");
        $finish;
    end

endmodule

Waveforms/dewhitener_test.vcd
$date
	Wed Apr 01 20:42:52 2026
$end
$version
	Icarus Verilog
$end
$timescale
	1ps
$end
$scope module data_dewhitener_tb $end
$var wire 1 ! whitened_data_ref $end
$var wire 1 " dewhitened_data_out $end
$var reg 6 # channel_index [5:0] $end
$var reg 1 $ clk $end
$var reg 1 % data_in $end
$var reg 1 & enable $end
$var reg 1 ' expected_dewhitened $end
$var reg 1 ( lfsr_load $end
$var reg 1 ) rst_n $end
$var reg 7 * tb_lfsr [6:0] $end
$var reg 40 + test_pattern [39:0] $end
$var integer 32 , i [31:0] $end
$scope module uut_dewhitener $end
$var wire 6 - channel_index [5:0] $end
$var wire 1 $ clk $end
$var wire 1 % data_in $end
$var wire 1 " dewhitened_data_out $end
$var wire 1 & enable $end
$var wire 1 ( lfsr_load $end
$var wire 1 ) rst_n $end
$var wire 7 . lfsr_seed [6:0] $end
$var wire 1 / lfsr_out_bit $end
$var wire 7 0 lfsr_next [6:0] $end
$var reg 7 1 lfsr [6:0] $end
$upscope $end
$scope module uut_whitener $end
$var wire 6 2 channel_index [5:0] $end
$var wire 1 $ clk $end
$var wire 1 " data_in $end
$var wire 1 & enable $end
$var wire 1 ( lfsr_load $end
$var wire 1 ) rst_n $end
$var wire 1 ! whitened_data_out $end
$var wire 7 3 lfsr_seed [6:0] $end
$var wire 1 4 lfsr_out_bit $end
$var wire 7 5 lfsr_next [6:0] $end
$var reg 7 6 lfsr [6:0] $end
$upscope $end
$scope task feed_and_check $end
$var reg 1 7 test_bit $end
$upscope $end
$scope task load_channel $end
$var reg 6 8 ch [5:0] $end
$upscope $end
$upscope $end
$enddefinitions $end
#0
$dumpvars
bx 8
x7
b1111111 6
b1101111 5
14
b0 3
b0 2
b1111111 1
b1101111 0
1/
b0 .
b0 -
bx ,
bx +
bx *
0)
0(
x'
0&
0%
0$
b0 #
1"
0!
$end
#25000
1$
#50000
0$
#75000
1$
#100000
0$
1)
#125000
1$
#150000
b1001010 *
1(
b1001010 .
b1001010 3
b100101 #
b100101 -
b100101 2
0$
b100101 8
#175000
0"
0!
b101 0
0/
b101 5
04
b1001010 1
b1001010 6
1$
#176000
17
b0 ,
b11010110001101 +
0(
#200000
1!
1"
1&
1%
0$
#201000
1'
#225000
0"
b1010 5
14
b1010 0
1/
b101 6
b101 1
07
b1 ,
b101 *
1$
#250000
0!
1"
0%
0$
#275000
0"
0!
b10100 0
0/
b10100 5
04
b1010 1
b1010 6
17
b10 ,
b1010 *
1$
#300000
1!
1"
1%
0$
#325000
b101000 5
b101000 0
b10100 6
b10100 1
b11 ,
b10100 *
1$
#350000
0$
#375000
b1010000 0
b1010000 5
b101000 1
b101000 6
07
b100 ,
b101000 *
1$
#400000
0!
0"
0%
0$
#401000
0'
#425000
b110001 5
b110001 0
b1010000 6
b1010000 1
b101 ,
b1010000 *
1$
#450000
0$
#475000
1"
0!
b1100010 0
1/
b1100010 5
14
b110001 1
b110001 6
b110 ,
b110001 *
1$
#500000
0$
#501000
1'
#525000
0"
b1010101 5
04
b1010101 0
0/
b1100010 6
b1100010 1
17
b111 ,
b1100010 *
1$
#550000
1!
1"
1%
0$
#575000
0"
1!
b111011 0
1/
b111011 5
14
b1010101 1
b1010101 6
b1000 ,
b1010101 *
1$
#600000
0$
#601000
0'
#625000
b1110110 5
b1110110 0
b111011 6
b111011 1
07
b1001 ,
b111011 *
1$
#650000
0!
1"
0%
0$
#651000
1'
#675000
0"
0!
b1111101 0
0/
b1111101 5
04
b1110110 1
b1110110 6
17
b1010 ,
b1110110 *
1$
#700000
1!
1"
1%
0$
#725000
0"
b1101011 5
14
b1101011 0
1/
b1111101 6
b1111101 1
07
b1011 ,
b1111101 *
1$
#750000
0!
1"
0%
0$
#775000
b1000111 0
b1000111 5
b1101011 1
b1101011 6
17
b1100 ,
b1101011 *
1$
#800000
1!
0"
1%
0$
#801000
0'
#825000
b11111 5
b11111 0
b1000111 6
b1000111 1
b1101 ,
b1000111 *
1$
#850000
0$
#875000
b111110 0
b111110 5
b11111 1
b11111 6
07
b1110 ,
b11111 *
1$
#900000
0!
1"
0%
0$
#901000
1'
#925000
0"
b1111100 5
04
b1111100 0
0/
b111110 6
b111110 1
b1111 ,
b111110 *
1$
#950000
0$
#951000
0'
#975000
0&
b10000 ,
b1111100 *
1$
#1000000
0$
#1025000
1$
#1050000
0$
#1075000
1$
#1100000
0$
#1125000
1$
b10101 8
#1150000
b101010 *
1(
b101010 .
b101010 3
b10101 #
b10101 -
b10101 2
0$
#1175000
b1010100 0
b1010100 5
b101010 1
b101010 6
1$
#1176000
b0 ,
0(
#1200000
1&
0$
#1225000
b111001 5
b111001 0
b1010100 6
b1010100 1
b1 ,
b1010100 *
1$
#1250000
0$
#1275000
1"
0!
b1110010 0
1/
b1110010 5
14
b111001 1
b111001 6
b10 ,
b111001 *
1$
#1300000
0$
#1301000
1'
#1325000
0"
b1110101 5
04
b1110101 0
0/
b1110010 6
b1110010 1
b11 ,
b1110010 *
1$
#1350000
0$
#1351000
0'
#1375000
1"
0!
b1111011 0
1/
b1111011 5
14
b1110101 1
b1110101 6
b100 ,
b1110101 *
1$
#1400000
0$
#1401000
1'
#1425000
b1100111 5
b1100111 0
b1111011 6
b1111011 1
b101 ,
b1111011 *
1$
#1450000
0$
#1475000
b1011111 0
b1011111 5
b1100111 1
b1100111 6
b110 ,
b1100111 *
1$
#1500000
0$
#1525000
b101111 5
b101111 0
b1011111 6
b1011111 1
b111 ,
b1011111 *
1$
#1550000
0$
#1575000
b1011110 0
b1011110 5
b101111 1
b101111 6
b1000 ,
b101111 *
1$
#1600000
0$
#1625000
0"
b101101 5
04
b101101 0
0/
b1011110 6
b1011110 1
b1001 ,
b1011110 *
1$
#1650000
0$
#1651000
0'
#1675000
0&
b1010 ,
b101101 *
1$
#1700000
0$
#1725000
1$
#1750000
0$
#1775000
1$
#1800000
0$
#1825000
1$
b110011 8
#1850000
b1100110 *
1(
b1100110 .
b1100110 3
b110011 #
b110011 -
b110011 2
0$
#1875000
b1011101 0
b1011101 5
b1100110 1
b1100110 6
1$
#1876000
17
b0 ,
0(
#1900000
1!
1"
1&
1%
0$
#1901000
1'
#1925000
0"
b101011 5
14
b101011 0
1/
b1011101 6
b1011101 1
b1 ,
b1011101 *
1$
#1950000
0$
#1951000
0'
#1975000
b1010110 0
b1010110 5
b101011 1
b101011 6
b10 ,
b101011 *
1$
#2000000
0$
#2025000
1"
b111101 5
04
b111101 0
0/
b1010110 6
b1010110 1
b11 ,
b1010110 *
1$
#2050000
0$
#2051000
1'
#2075000
0"
1!
b1111010 0
1/
b1111010 5
14
b111101 1
b111101 6
b100 ,
b111101 *
1$
#2100000
0$
#2101000
0'
#2125000
1"
b1100101 5
04
b1100101 0
0/
b1111010 6
b1111010 1
b101 ,
b1111010 *
1$
#2150000
0$
#2151000
1'
#2175000
0"
1!
b1011011 0
1/
b1011011 5
14
b1100101 1
b1100101 6
b110 ,
b1100101 *
1$
#2200000
0$
#2201000
0'
#2225000
b100111 5
b100111 0
b1011011 6
b1011011 1
b111 ,
b1011011 *
1$
#2250000
0$
#2275000
b1001110 0
b1001110 5
b100111 1
b100111 6
b1000 ,
b100111 *
1$
#2300000
0$
#2325000
1"
b1101 5
04
b1101 0
0/
b1001110 6
b1001110 1
b1001 ,
b1001110 *
1$
#2350000
0$
#2351000
1'
#2375000
0&
b1010 ,
b1101 *
1$
