Verilog_files/Receiver_packet_parser.v
/**
 * @module Receiver_packet_parser
 * @brief BLE Packet Parser for the Receiver
 */
module Receiver_packet_parser #(
    parameter [31:0] ACCESS_ADDR = 32'h8E89BED6,
    parameter [5:0]  CHANNEL_IDX = 6'd37
)(
    input  wire        clk,
    input  wire        rst_n,
    input  wire        data_in,
    input  wire        data_valid,
    
    output reg         rx_ready,
    output reg         packet_complete,
    output reg         crc_valid,
    output reg  [7:0]  rx_data_out,
    output reg         rx_data_valid,
    output reg  [7:0]  payload_length,
    output wire [5:0]  channel_index_out
);

    localparam IDLE         = 3'd0,
               ADDR_SYNC    = 3'd1,
               HEADER_RX    = 3'd2,
               PAYLOAD_RX   = 3'd3,
               CRC_RX       = 3'd4,
               CRC_CHECK    = 3'd5,
               DONE         = 3'd6;

    reg [2:0]  state;
    reg [7:0]  bit_cnt;
    reg [7:0]  byte_cnt;
    reg [7:0]  shift_reg;
    reg [31:0] addr_shift;
    reg [23:0] crc_calc;
    reg [23:0] crc_received;
    reg [7:0]  payload_idx;

    // --- CRC24 Logic (Must match BLE spec, not CRC16) ---
    wire [23:0] crc_next;
    wire        crc_feedback;
    assign channel_index_out = CHANNEL_IDX;

    // Polynomial: x^24 + x^10 + x^9 + x^6 + x^4 + x^3 + x + 1
    assign crc_feedback = data_in ^ crc_calc[0];
    assign crc_next[0]  = crc_calc[1]  ^ crc_feedback;
    assign crc_next[1]  = crc_calc[2];
    assign crc_next[2]  = crc_calc[3]  ^ crc_feedback;
    assign crc_next[3]  = crc_calc[4]  ^ crc_feedback;
    assign crc_next[4]  = crc_calc[5];
    assign crc_next[5]  = crc_calc[6]  ^ crc_feedback;
    assign crc_next[6]  = crc_calc[7];
    assign crc_next[7]  = crc_calc[8];
    assign crc_next[8]  = crc_calc[9]  ^ crc_feedback;
    assign crc_next[9]  = crc_calc[10] ^ crc_feedback;
    assign crc_next[10] = crc_calc[11];
    assign crc_next[11] = crc_calc[12];
    assign crc_next[12] = crc_calc[13];
    assign crc_next[13] = crc_calc[14];
    assign crc_next[14] = crc_calc[15];
    assign crc_next[15] = crc_calc[16];
    assign crc_next[16] = crc_calc[17];
    assign crc_next[17] = crc_calc[18];
    assign crc_next[18] = crc_calc[19];
    assign crc_next[19] = crc_calc[20];
    assign crc_next[20] = crc_calc[21];
    assign crc_next[21] = crc_calc[22];
    assign crc_next[22] = crc_calc[23];
    assign crc_next[23] = crc_feedback;

    always @(posedge clk or negedge rst_n) begin
        if (!rst_n) begin
            state           <= IDLE;
            bit_cnt         <= 0;
            byte_cnt        <= 0;
            shift_reg       <= 0;
            addr_shift      <= 0;
            rx_ready        <= 1;
            packet_complete <= 0;
            crc_valid       <= 0;
            rx_data_valid   <= 0;
            crc_calc        <= 24'h555555;
            payload_length  <= 0;
        end else begin
            rx_data_valid   <= 0;
            packet_complete <= 0;
            
            if (data_valid) begin
                case (state)
                    // === 1. IDLE: Hunt for 8-bit Preamble ===
                    IDLE: begin
                        shift_reg <= {data_in, shift_reg[7:1]};
                        crc_calc  <= 24'h555555; // Keep reset until PDU starts
                        
                        if ({data_in, shift_reg[7:1]} == 8'hAA || {data_in, shift_reg[7:1]} == 8'h55) begin
                            state      <= ADDR_SYNC;
                            bit_cnt    <= 0;
                            addr_shift <= 0;
                            $display("[RX] Preamble matched: %h", {data_in, shift_reg[7:1]});
                        end
                    end

                    // === 2. ADDR_SYNC: Hunt for 32-bit Access Address ===
                    ADDR_SYNC: begin
                        addr_shift <= {data_in, addr_shift[31:1]};
                        bit_cnt    <= bit_cnt + 8'd1;
                        
                        if (bit_cnt == 31) begin
                            if ({data_in, addr_shift[31:1]} == ACCESS_ADDR) begin
                                state    <= HEADER_RX;
                                bit_cnt  <= 0;
                                byte_cnt <= 0;
                                $display("[RX] Access Address matched: %h", ACCESS_ADDR);
                            end else begin
                                state <= IDLE; // False alarm, back to hunting
                            end
                        end
                    end

                    // === 3. HEADER_RX: Capture 2 bytes ===
                    HEADER_RX: begin
                        shift_reg <= {data_in, shift_reg[7:1]};
                        crc_calc  <= crc_next; // Start CRC
                        bit_cnt   <= bit_cnt + 8'd1;
                        
                        if (bit_cnt == 7) begin
                            bit_cnt <= 0;
                            if (byte_cnt == 0) begin
                                byte_cnt <= 1;
                                $display("[RX] Header Byte 1 (Flags): %h", {data_in, shift_reg[7:1]});
                            end else begin
                                payload_length <= {data_in, shift_reg[7:1]};
                                payload_idx    <= 0;
                                state          <= PAYLOAD_RX;
                                $display("[RX] Header Byte 2 (Length): %d bytes", {data_in, shift_reg[7:1]});
                            end
                        end
                    end

                    // === 4. PAYLOAD_RX: Variable length data ===
                    PAYLOAD_RX: begin
                        shift_reg <= {data_in, shift_reg[7:1]};
                        crc_calc  <= crc_next;
                        bit_cnt   <= bit_cnt + 8'd1;
                        
                        if (bit_cnt == 7) begin
                            bit_cnt       <= 0;
                            rx_data_out   <= {data_in, shift_reg[7:1]};
                            rx_data_valid <= 1;
                            
                            if (payload_idx == (payload_length - 1)) begin
                                state   <= CRC_RX;
                                bit_cnt <= 0;
                            end else begin
                                payload_idx <= payload_idx + 8'd1;
                            end
                        end
                    end

                    // === 5. CRC_RX: Capture 24 bits ===
                    CRC_RX: begin
                        crc_received <= {data_in, crc_received[23:1]}; // LSB first shift
                        bit_cnt      <= bit_cnt + 8'd1;
                        
                        if (bit_cnt == 23) begin
                            state   <= CRC_CHECK;
                            bit_cnt <= 0;
                        end
                    end

                    // === 6. CRC_CHECK (Combinational cycle) ===
                    CRC_CHECK: begin
                        if (crc_received == crc_calc) begin
                            crc_valid <= 1;
                            $display("[RX] CRC VALID. Calculated: %h | Received: %h", crc_calc, crc_received);
                        end else begin
                            crc_valid <= 0;
                            $display("[RX] CRC INVALID. Calculated: %h | Received: %h", crc_calc, crc_received);
                        end
                        state <= DONE;
                    end

                    // === 7. DONE ===
                    DONE: begin
                        packet_complete <= 1;
                        state           <= IDLE;
                    end
                endcase
            end
        end
    end
endmodule

Testbenches/Receiver_packet_parser_tb.v
`timescale 1ns / 1ps

module Receiver_packet_parser_tb;

    reg        clk;
    reg        rst_n;
    reg        data_in;
    reg        data_valid;

    wire        rx_ready;
    wire        packet_complete;
    wire        crc_valid;
    wire [7:0]  rx_data_out;
    wire        rx_data_valid;
    wire [7:0]  payload_length;
    wire [5:0]  channel_index_out;

    // --- Instantiate the Packet Parser ---
    Receiver_packet_parser #(
        .ACCESS_ADDR(32'h8E89BED6),
        .CHANNEL_IDX(6'd37)
    ) uut_parser (
        .clk(clk),
        .rst_n(rst_n),
        .data_in(data_in),
        .data_valid(data_valid),
        .rx_ready(rx_ready),
        .packet_complete(packet_complete),
        .crc_valid(crc_valid),
        .rx_data_out(rx_data_out),
        .rx_data_valid(rx_data_valid),
        .payload_length(payload_length),
        .channel_index_out(channel_index_out)
    );

    // --- Clock Generator (20MHz -> 50ns period) ---
    parameter CLK_PERIOD = 50;
    initial clk = 0;
    always #(CLK_PERIOD/2) clk = ~clk;

    // --- RX Monitor Thread ---
    always @(posedge clk) begin
        if (rx_data_valid) begin
            $display("[RX THREAD] Extracted Payload Byte: %02X", rx_data_out);
        end
        if (packet_complete) begin
            $display("[RX THREAD] Packet fully parsed and passed to MAC layer!");
        end
    end

    // =========================================================
    // TESTBENCH DYNAMIC CRC ENGINE
    // =========================================================
    reg [23:0] tb_crc;
    reg crc_fb;

    // Task to send Header/Payload bytes AND calculate the CRC simultaneously
    task send_pdu_byte(input [7:0] byte_val);
        integer i;
        begin
            for (i = 0; i < 8; i = i + 1) begin
                @(negedge clk);
                data_in = byte_val[i];
                data_valid = 1;

                // Calculate next CRC state to match the hardware LFSR
                crc_fb = byte_val[i] ^ tb_crc[0];
                tb_crc = {
                    crc_fb,               // [23]
                    tb_crc[23],           // [22]
                    tb_crc[22],           // [21]
                    tb_crc[21],           // [20]
                    tb_crc[20],           // [19]
                    tb_crc[19],           // [18]
                    tb_crc[18],           // [17]
                    tb_crc[17],           // [16]
                    tb_crc[16],           // [15]
                    tb_crc[15],           // [14]
                    tb_crc[14],           // [13]
                    tb_crc[13],           // [12]
                    tb_crc[12],           // [11]
                    tb_crc[11],           // [10]
                    tb_crc[10] ^ crc_fb,  // [9]
                    tb_crc[9]  ^ crc_fb,  // [8]
                    tb_crc[8],            // [7]
                    tb_crc[7],            // [6]
                    tb_crc[6]  ^ crc_fb,  // [5]
                    tb_crc[5],            // [4]
                    tb_crc[4]  ^ crc_fb,  // [3]
                    tb_crc[3]  ^ crc_fb,  // [2]
                    tb_crc[2],            // [1]
                    tb_crc[1]  ^ crc_fb   // [0]
                };
            end
        end
    endtask

    // Task to send the final calculated CRC
    task send_dynamic_crc();
        integer i;
        begin
            $display("[TX THREAD] Sending auto-calculated CRC: %06X", tb_crc);
            for (i = 0; i < 24; i = i + 1) begin
                @(negedge clk);
                data_in = tb_crc[i];
                data_valid = 1;
            end
        end
    endtask

    // --- Standard Helper Tasks (No CRC math needed here) ---
    task send_byte(input [7:0] byte_val);
        integer i;
        begin
            for (i = 0; i < 8; i = i + 1) begin
                @(negedge clk);
                data_in = byte_val[i];
                data_valid = 1;
            end
        end
    endtask

    task send_word(input [31:0] word_val);
        integer i;
        begin
            for (i = 0; i < 32; i = i + 1) begin
                @(negedge clk);
                data_in = word_val[i];
                data_valid = 1;
            end
        end
    endtask

    // --- Main Test Sequence ---
    initial begin
        $dumpfile("parser_test.vcd");
        $dumpvars(0, Receiver_packet_parser_tb);

        $display("=== Starting Packet Parser Verification ===");
        rst_n = 0;
        data_in = 0;
        data_valid = 0;
        #(CLK_PERIOD * 2);
        rst_n = 1;
        #(CLK_PERIOD * 2);

        $display("\n--- Sending Preamble (0xAA) ---");
        send_byte(8'hAA);

        $display("\n--- Sending Access Address (0x8E89BED6) ---");
        send_word(32'h8E89BED6);

        // --- Start of PDU (Protocol Data Unit) ---
        // We must initialize the CRC to the BLE default before sending the header
        tb_crc = 24'h555555; 

        $display("\n--- Sending Header ---");
        send_pdu_byte(8'h02); 
        send_pdu_byte(8'h05); 

        $display("\n--- Sending Payload ---");
        // You can change these to ANY values, and the testbench will automatically adapt!
        send_pdu_byte(8'h39);
        send_pdu_byte(8'h41);
        send_pdu_byte(8'h43);
        send_pdu_byte(8'h44);
        send_pdu_byte(8'haa);

        $display("\n--- Sending CRC ---");
        send_dynamic_crc(); 

        // Let FSM wrap up
        @(negedge clk);
        data_in = 0; 
        @(negedge clk);
        @(negedge clk);
        data_valid = 0;

        #(CLK_PERIOD * 10);
        $display("\n=== Packet Parser Verification Complete ===");
        $finish;
    end
endmodule

Waveforms/parser_test.vcd
$date
	Wed Apr 01 21:23:27 2026
$end
$version
	Icarus Verilog
$end
$timescale
	1ps
$end
$scope module Receiver_packet_parser_tb $end
$var wire 6 ! channel_index_out [5:0] $end
$var wire 1 " rx_ready $end
$var wire 1 # rx_data_valid $end
$var wire 8 $ rx_data_out [7:0] $end
$var wire 8 % payload_length [7:0] $end
$var wire 1 & packet_complete $end
$var wire 1 ' crc_valid $end
$var reg 1 ( clk $end
$var reg 1 ) crc_fb $end
$var reg 1 * data_in $end
$var reg 1 + data_valid $end
$var reg 1 , rst_n $end
$var reg 24 - tb_crc [23:0] $end
$scope module uut_parser $end
$var wire 6 . channel_index_out [5:0] $end
$var wire 1 ( clk $end
$var wire 1 / crc_feedback $end
$var wire 1 * data_in $end
$var wire 1 + data_valid $end
$var wire 1 , rst_n $end
$var wire 24 0 crc_next [23:0] $end
$var reg 32 1 addr_shift [31:0] $end
$var reg 8 2 bit_cnt [7:0] $end
$var reg 8 3 byte_cnt [7:0] $end
$var reg 24 4 crc_calc [23:0] $end
$var reg 24 5 crc_received [23:0] $end
$var reg 1 ' crc_valid $end
$var reg 1 & packet_complete $end
$var reg 8 6 payload_idx [7:0] $end
$var reg 8 7 payload_length [7:0] $end
$var reg 8 8 rx_data_out [7:0] $end
$var reg 1 # rx_data_valid $end
$var reg 1 " rx_ready $end
$var reg 8 9 shift_reg [7:0] $end
$var reg 3 : state [2:0] $end
$upscope $end
$scope task send_byte $end
$var reg 8 ; byte_val [7:0] $end
$var integer 32 < i [31:0] $end
$upscope $end
$scope task send_dynamic_crc $end
$var integer 32 = i [31:0] $end
$upscope $end
$scope task send_pdu_byte $end
$var reg 8 > byte_val [7:0] $end
$var integer 32 ? i [31:0] $end
$upscope $end
$scope task send_word $end
$var reg 32 @ word_val [31:0] $end
$var integer 32 A i [31:0] $end
$upscope $end
$upscope $end
$enddefinitions $end
#0
$dumpvars
bx A
bx @
bx ?
bx >
bx =
bx <
bx ;
b0 :
b0 9
bx 8
b0 7
bx 6
bx 5
b10101010101010101010101 4
b0 3
b0 2
b0 1
b101010101010100110000111 0
1/
b100101 .
bx -
0,
0+
0*
x)
0(
0'
0&
b0 %
bx $
0#
1"
b100101 !
$end
#25000
1(
#50000
0(
#75000
1(
#100000
0(
1,
#125000
1(
#150000
0(
#175000
1(
#200000
1+
0(
b1 <
b10101010 ;
#225000
1(
#250000
b1010101010101010101010 0
0/
b10 <
1*
0(
#275000
b10000000 9
1(
#300000
b101010101010100110000111 0
1/
b11 <
0*
0(
#325000
b1000000 9
1(
#350000
b1010101010101010101010 0
0/
b100 <
1*
0(
#375000
b10100000 9
1(
#400000
b101010101010100110000111 0
1/
b101 <
0*
0(
#425000
b1010000 9
1(
#450000
b1010101010101010101010 0
0/
b110 <
1*
0(
#475000
b10101000 9
1(
#500000
b101010101010100110000111 0
1/
b111 <
0*
0(
#525000
b1010100 9
1(
#550000
b1010101010101010101010 0
0/
b0 A
b10001110100010011011111011010110 @
b1000 <
1*
0(
#575000
b1 :
b10101010 9
1(
#600000
b101010101010100110000111 0
1/
b1 A
0*
0(
#625000
b1 2
1(
#650000
b1010101010101010101010 0
0/
b10 A
1*
0(
#675000
b10 2
b10000000000000000000000000000000 1
1(
#700000
b11 A
0(
#725000
b11 2
b11000000000000000000000000000000 1
1(
#750000
b101010101010100110000111 0
1/
b100 A
0*
0(
#775000
b100 2
b1100000000000000000000000000000 1
1(
#800000
b1010101010101010101010 0
0/
b101 A
1*
0(
#825000
b101 2
b10110000000000000000000000000000 1
1(
#850000
b101010101010100110000111 0
1/
b110 A
0*
0(
#875000
b110 2
b1011000000000000000000000000000 1
1(
#900000
b1010101010101010101010 0
0/
b111 A
1*
0(
#925000
b111 2
b10101100000000000000000000000000 1
1(
#950000
b1000 A
0(
#975000
b1000 2
b11010110000000000000000000000000 1
1(
#1000000
b101010101010100110000111 0
1/
b1001 A
0*
0(
#1025000
b1001 2
b1101011000000000000000000000000 1
1(
#1050000
b1010101010101010101010 0
0/
b1010 A
1*
0(
#1075000
b1010 2
b10110101100000000000000000000000 1
1(
#1100000
b1011 A
0(
#1125000
b1011 2
b11011010110000000000000000000000 1
1(
#1150000
b1100 A
0(
#1175000
b1100 2
b11101101011000000000000000000000 1
1(
#1200000
b1101 A
0(
#1225000
b1101 2
b11110110101100000000000000000000 1
1(
#1250000
b1110 A
0(
#1275000
b1110 2
b11111011010110000000000000000000 1
1(
#1300000
b101010101010100110000111 0
1/
b1111 A
0*
0(
#1325000
b1111 2
b1111101101011000000000000000000 1
1(
#1350000
b1010101010101010101010 0
0/
b10000 A
1*
0(
#1375000
b10000 2
b10111110110101100000000000000000 1
1(
#1400000
b10001 A
0(
#1425000
b10001 2
b11011111011010110000000000000000 1
1(
#1450000
b101010101010100110000111 0
1/
b10010 A
0*
0(
#1475000
b10010 2
b1101111101101011000000000000000 1
1(
#1500000
b10011 A
0(
#1525000
b10011 2
b110111110110101100000000000000 1
1(
#1550000
b1010101010101010101010 0
0/
b10100 A
1*
0(
#1575000
b10100 2
b10011011111011010110000000000000 1
1(
#1600000
b101010101010100110000111 0
1/
b10101 A
0*
0(
#1625000
b10101 2
b1001101111101101011000000000000 1
1(
#1650000
b10110 A
0(
#1675000
b10110 2
b100110111110110101100000000000 1
1(
#1700000
b10111 A
0(
#1725000
b10111 2
b10011011111011010110000000000 1
1(
#1750000
b1010101010101010101010 0
0/
b11000 A
1*
0(
#1775000
b11000 2
b10001001101111101101011000000000 1
1(
#1800000
b101010101010100110000111 0
1/
b11001 A
0*
0(
#1825000
b11001 2
b1000100110111110110101100000000 1
1(
#1850000
b1010101010101010101010 0
0/
b11010 A
1*
0(
#1875000
b11010 2
b10100010011011111011010110000000 1
1(
#1900000
b11011 A
0(
#1925000
b11011 2
b11010001001101111101101011000000 1
1(
#1950000
b11100 A
0(
#1975000
b11100 2
b11101000100110111110110101100000 1
1(
#2000000
b101010101010100110000111 0
1/
b11101 A
0*
0(
#2025000
b11101 2
b1110100010011011111011010110000 1
1(
#2050000
b11110 A
0(
#2075000
b11110 2
b111010001001101111101101011000 1
1(
#2100000
b11111 A
0(
#2125000
b11111 2
b11101000100110111110110101100 1
1(
#2150000
b1010101010101010101010 0
0/
b0 ?
b10 >
b10101010101010101010101 -
b100000 A
1*
0(
#2175000
b10 :
b0 2
b10001110100010011011111011010110 1
1(
#2200000
b101010101010100110000111 0
1/
b1 ?
b101010101010100110000111 -
1)
0*
0(
#2225000
b110101010101011111101110 0
b1 2
b101010101010100110000111 4
b1010101 9
1(
#2250000
b10101010101010011000011 0
0/
b10 ?
b10101010101010011000011 -
0)
1*
0(
#2275000
b1010101010101001100001 0
b10 2
b10101010101010011000011 4
b10101010 9
1(
#2300000
b101010101010100101001100 0
1/
b11 ?
b101010101010100101001100 -
1)
0*
0(
#2325000
0/
b10101010101010010100110 0
b11 2
b101010101010100101001100 4
b1010101 9
1(
#2350000
b100 ?
b10101010101010010100110 -
0)
0(
#2375000
b1010101010101001010011 0
b100 2
b10101010101010010100110 4
b101010 9
1(
#2400000
b101 ?
b1010101010101001010011 -
0(
#2425000
1/
b100101010101011000000100 0
b101 2
b1010101010101001010011 4
b10101 9
1(
#2450000
b110 ?
b100101010101011000000100 -
1)
0(
#2475000
0/
b10010101010101100000010 0
b110 2
b100101010101011000000100 4
b1010 9
1(
#2500000
b111 ?
b10010101010101100000010 -
0)
0(
#2525000
b1001010101010110000001 0
b111 2
b10010101010101100000010 4
b101 9
1(
#2550000
b101 >
b0 ?
b1001010101010110000001 -
0(
#2575000
1/
b100100101010100111101101 0
b1 3
b0 2
b1001010101010110000001 4
b10 9
1(
#2600000
b100101010101011000000 0
0/
b1 ?
b100101010101011000000 -
1*
0(
#2625000
1/
b100010010101011001001101 0
b1 2
b100101010101011000000 4
b10000001 9
1(
#2650000
b10010101010101100000 0
0/
b10 ?
b10010101010101100000 -
0*
0(
#2675000
b1001010101010110000 0
b10 2
b10010101010101100000 4
b1000000 9
1(
#2700000
b100001001010100110011101 0
1/
b11 ?
b100001001010100110011101 -
1)
1*
0(
#2725000
0/
b10000100101010011001110 0
b11 2
b100001001010100110011101 4
b10100000 9
1(
#2750000
b110000100101011111100011 0
1/
b100 ?
b110000100101011111100011 -
0*
0(
#2775000
b111000010010100011011100 0
b100 2
b110000100101011111100011 4
b1010000 9
1(
#2800000
b101 ?
b111000010010100011011100 -
0(
#2825000
0/
b11100001001010001101110 0
b101 2
b111000010010100011011100 4
b101000 9
1(
#2850000
b110 ?
b11100001001010001101110 -
0)
0(
#2875000
b1110000100101000110111 0
b110 2
b11100001001010001101110 4
b10100 9
1(
#2900000
b111 ?
b1110000100101000110111 -
0(
#2925000
1/
b100111000010011000110110 0
b111 2
b1110000100101000110111 4
b1010 9
1(
#2950000
b111001 >
b0 ?
b100111000010011000110110 -
1)
0(
#2975000
0/
b10011100001001100011011 0
b11 :
b0 6
b101 %
b101 7
b0 2
b100111000010011000110110 4
b101 9
1(
#3000000
b110011100001000000110110 0
1/
b1 ?
b110011100001000000110110 -
1*
0(
#3025000
b111001110000101100110110 0
b1 2
b110011100001000000110110 4
b10000010 9
1(
#3050000
b11001110000100000011011 0
0/
b10 ?
b11001110000100000011011 -
0)
0*
0(
#3075000
1/
b101100111000011100100000 0
b10 2
b11001110000100000011011 4
b1000001 9
1(
#3100000
b11 ?
b101100111000011100100000 -
1)
0(
#3125000
0/
b10110011100001110010000 0
b11 2
b101100111000011100100000 4
b100000 9
1(
#3150000
b110110011100000010111101 0
1/
b100 ?
b110110011100000010111101 -
1*
0(
#3175000
0/
b11011001110000001011110 0
b100 2
b110110011100000010111101 4
b10010000 9
1(
#3200000
b101 ?
b11011001110000001011110 -
0)
0(
#3225000
1/
b101101100111001100000010 0
b101 2
b11011001110000001011110 4
b11001000 9
1(
#3250000
b110 ?
b101101100111001100000010 -
1)
0(
#3275000
b110110110011101010101100 0
b110 2
b101101100111001100000010 4
b11100100 9
1(
#3300000
b10110110011100110000001 0
0/
b111 ?
b10110110011100110000001 -
0)
0*
0(
#3325000
1/
b101011011001111111101101 0
b111 2
b10110110011100110000001 4
b1110010 9
1(
#3350000
b1000001 >
b0 ?
b101011011001111111101101 -
1)
0(
#3375000
b110101101100110011011011 0
b1 6
1#
b111001 $
b111001 8
b0 2
b101011011001111111101101 4
b111001 9
1(
#3400000
b10101101100111111110110 0
0/
b1 ?
b10101101100111111110110 -
0)
1*
0(
#3425000
1/
b101010110110010011010110 0
b1 2
b10101101100111111110110 4
b10011100 9
0#
1(
#3450000
b1010110110011111111011 0
0/
b10 ?
b1010110110011111111011 -
0*
0(
#3475000
1/
b100101011011000011010000 0
b10 2
b1010110110011111111011 4
b1001110 9
1(
#3500000
b11 ?
b100101011011000011010000 -
1)
0(
#3525000
0/
b10010101101100001101000 0
b11 2
b100101011011000011010000 4
b100111 9
1(
#3550000
b100 ?
b10010101101100001101000 -
0)
0(
#3575000
b1001010110110000110100 0
b100 2
b10010101101100001101000 4
b10011 9
1(
#3600000
b101 ?
b1001010110110000110100 -
0(
#3625000
b100101011011000011010 0
b101 2
b1001010110110000110100 4
b1001 9
1(
#3650000
b110 ?
b100101011011000011010 -
0(
#3675000
b10010101101100001101 0
b110 2
b100101011011000011010 4
b100 9
1(
#3700000
b100010010101100000100000 0
1/
b111 ?
b100010010101100000100000 -
1)
1*
0(
#3725000
b110001001010111100111101 0
b111 2
b100010010101100000100000 4
b10000010 9
1(
#3750000
b10001001010110000010000 0
0/
b1000011 >
b0 ?
b10001001010110000010000 -
0)
0*
0(
#3775000
b1000100101011000001000 0
b10 6
1#
b1000001 $
b1000001 8
b0 2
b10001001010110000010000 4
b1000001 9
1(
#3800000
b101000100101010100100101 0
1/
b1 ?
b101000100101010100100101 -
1)
1*
0(
#3825000
0/
b10100010010101010010010 0
b1 2
b101000100101010100100101 4
b10100000 9
0#
1(
#3850000
b10 ?
b10100010010101010010010 -
0)
0(
#3875000
1/
b101010001001011001100100 0
b10 2
b10100010010101010010010 4
b11010000 9
1(
#3900000
b1010001001010101001001 0
0/
b11 ?
b1010001001010101001001 -
0*
0(
#3925000
1/
b100101000100100110001001 0
b11 2
b1010001001010101001001 4
b1101000 9
1(
#3950000
b100 ?
b100101000100100110001001 -
1)
0(
#3975000
b110010100010011111101001 0
b100 2
b100101000100100110001001 4
b110100 9
1(
#4000000
b101 ?
b110010100010011111101001 -
0(
#4025000
b111001010001000011011001 0
b101 2
b110010100010011111101001 4
b11010 9
1(
#4050000
b110 ?
b111001010001000011011001 -
0(
#4075000
b111100101000101101000001 0
b110 2
b111001010001000011011001 4
b1101 9
1(
#4100000
b11100101000100001101100 0
0/
b111 ?
b11100101000100001101100 -
0)
1*
0(
#4125000
1/
b101110010100011100011011 0
b111 2
b11100101000100001101100 4
b10000110 9
1(
#4150000
b1110010100010000110110 0
0/
b1000100 >
b0 ?
b1110010100010000110110 -
0*
0(
#4175000
b111001010001000011011 0
b11 6
1#
b1000011 $
b1000011 8
b0 2
b1110010100010000110110 4
b1000011 9
1(
#4200000
b1 ?
b111001010001000011011 -
0(
#4225000
1/
b100011100101001000100000 0
b1 2
b111001010001000011011 4
b100001 9
0#
1(
#4250000
b10 ?
b100011100101001000100000 -
1)
0(
#4275000
0/
b10001110010100100010000 0
b10 2
b100011100101001000100000 4
b10000 9
1(
#4300000
b110001110010101000111101 0
1/
b11 ?
b110001110010101000111101 -
1*
0(
#4325000
0/
b11000111001010100011110 0
b11 2
b110001110010101000111101 4
b10001000 9
1(
#4350000
b111000111001011000110011 0
1/
b100 ?
b111000111001011000110011 -
0*
0(
#4375000
b111100011100100000110100 0
b100 2
b111000111001011000110011 4
b1000100 9
1(
#4400000
b101 ?
b111100011100100000110100 -
0(
#4425000
0/
b11110001110010000011010 0
b101 2
b111100011100100000110100 4
b100010 9
1(
#4450000
b110 ?
b11110001110010000011010 -
0)
0(
#4475000
b1111000111001000001101 0
b110 2
b11110001110010000011010 4
b10001 9
1(
#4500000
b101111000111000100100000 0
1/
b111 ?
b101111000111000100100000 -
1)
1*
0(
#4525000
b110111100011101110111101 0
b111 2
b101111000111000100100000 4
b10001000 9
1(
#4550000
b10111100011100010010000 0
0/
b10101010 >
b0 ?
b10111100011100010010000 -
0)
0*
0(
#4575000
b1011110001110001001000 0
b100 6
1#
b1000100 $
b1000100 8
b0 2
b10111100011100010010000 4
b1000100 9
1(
#4600000
b1 ?
b1011110001110001001000 -
0(
#4625000
b101111000111000100100 0
b1 2
b1011110001110001001000 4
b100010 9
0#
1(
#4650000
b100101111000110100001001 0
1/
b10 ?
b100101111000110100001001 -
1)
1*
0(
#4675000
0/
b10010111100011010000100 0
b10 2
b100101111000110100001001 4
b10010001 9
1(
#4700000
b110010111100010110101001 0
1/
b11 ?
b110010111100010110101001 -
0*
0(
#4725000
b111001011110000111111001 0
b11 2
b110010111100010110101001 4
b1001000 9
1(
#4750000
b11001011110001011010100 0
0/
b100 ?
b11001011110001011010100 -
0)
1*
0(
#4775000
1/
b101100101111001001000111 0
b100 2
b11001011110001011010100 4
b10100100 9
1(
#4800000
b1100101111000101101010 0
0/
b101 ?
b1100101111000101101010 -
0*
0(
#4825000
b110010111100010110101 0
b101 2
b1100101111000101101010 4
b1010010 9
1(
#4850000
b100110010111101110011000 0
1/
b110 ?
b100110010111101110011000 -
1)
1*
0(
#4875000
b110011001011111011100001 0
b110 2
b100110010111101110011000 4
b10101001 9
1(
#4900000
b10011001011110111001100 0
0/
b111 ?
b10011001011110111001100 -
0)
0*
0(
#4925000
b1001100101111011100110 0
b111 2
b10011001011110111001100 4
b1010100 9
1(
#4950000
b101001100101110111001011 0
1/
b0 =
b1000 ?
b101001100101110111001011 -
1)
1*
0(
#4975000
0/
b10100110010111011100101 0
b100 :
1#
b10101010 $
b10101010 8
b0 2
b101001100101110111001011 4
b10101010 9
1(
#5000000
b1 =
0(
#5025000
b1 2
b1xxxxxxxxxxxxxxxxxxxxxxx 5
0#
1(
#5050000
b10 =
0(
#5075000
b10 2
b11xxxxxxxxxxxxxxxxxxxxxx 5
1(
#5100000
b110100110010110111001000 0
1/
b11 =
0*
0(
#5125000
b11 2
b11xxxxxxxxxxxxxxxxxxxxx 5
1(
#5150000
b10100110010111011100101 0
0/
b100 =
1*
0(
#5175000
b100 2
b1011xxxxxxxxxxxxxxxxxxxx 5
1(
#5200000
b110100110010110111001000 0
1/
b101 =
0*
0(
#5225000
b101 2
b1011xxxxxxxxxxxxxxxxxxx 5
1(
#5250000
b110 =
0(
#5275000
b110 2
b1011xxxxxxxxxxxxxxxxxx 5
1(
#5300000
b10100110010111011100101 0
0/
b111 =
1*
0(
#5325000
b111 2
b1001011xxxxxxxxxxxxxxxxx 5
1(
#5350000
b1000 =
0(
#5375000
b1000 2
b11001011xxxxxxxxxxxxxxxx 5
1(
#5400000
b1001 =
0(
#5425000
b1001 2
b111001011xxxxxxxxxxxxxxx 5
1(
#5450000
b110100110010110111001000 0
1/
b1010 =
0*
0(
#5475000
b1010 2
b111001011xxxxxxxxxxxxxx 5
1(
#5500000
b10100110010111011100101 0
0/
b1011 =
1*
0(
#5525000
b1011 2
b10111001011xxxxxxxxxxxxx 5
1(
#5550000
b1100 =
0(
#5575000
b1100 2
b110111001011xxxxxxxxxxxx 5
1(
#5600000
b1101 =
0(
#5625000
b1101 2
b1110111001011xxxxxxxxxxx 5
1(
#5650000
b110100110010110111001000 0
1/
b1110 =
0*
0(
#5675000
b1110 2
b1110111001011xxxxxxxxxx 5
1(
#5700000
b10100110010111011100101 0
0/
b1111 =
1*
0(
#5725000
b1111 2
b101110111001011xxxxxxxxx 5
1(
#5750000
b110100110010110111001000 0
1/
b10000 =
0*
0(
#5775000
b10000 2
b101110111001011xxxxxxxx 5
1(
#5800000
b10001 =
0(
#5825000
b10001 2
b101110111001011xxxxxxx 5
1(
#5850000
b10100110010111011100101 0
0/
b10010 =
1*
0(
#5875000
b10010 2
b100101110111001011xxxxxx 5
1(
#5900000
b10011 =
0(
#5925000
b10011 2
b1100101110111001011xxxxx 5
1(
#5950000
b110100110010110111001000 0
1/
b10100 =
0*
0(
#5975000
b10100 2
b1100101110111001011xxxx 5
1(
#6000000
b10101 =
0(
#6025000
b10101 2
b1100101110111001011xxx 5
1(
#6050000
b10100110010111011100101 0
0/
b10110 =
1*
0(
#6075000
b10110 2
b1001100101110111001011xx 5
1(
#6100000
b110100110010110111001000 0
1/
b10111 =
0*
0(
#6125000
b10111 2
b1001100101110111001011x 5
1(
#6150000
b10100110010111011100101 0
0/
b11000 =
1*
0(
#6175000
b101 :
b0 2
b101001100101110111001011 5
1(
#6200000
b110100110010110111001000 0
1/
0*
0(
#6225000
b110 :
1'
1(
#6250000
0(
#6275000
b0 :
1&
1(
#6300000
0+
0(
#6325000
0&
1(
