Verilog_files/crc24_gen.v
/**
 * @module crc24_gen
 * @brief Implements the BLE 24-bit CRC
 */
module crc24_gen (
    clk,
    rst_n,
    enable,
    data_in,
    crc_out
);

    // --- Port Declarations ---
    input        clk;
    input        rst_n;
    input        enable;
    input        data_in;
    output [23:0] crc_out;

    // --- Internal Signals ---
    reg [23:0] crc_out;
    reg [23:0] crc_next;
    reg        feedback;

    localparam [23:0] CRC_INIT = 24'h555555;

    // --- Process 1: Combinational Logic (Calculator) ---
    // This logic implements the LSB-first CRC calculation.
 always @(*) begin
        
        // 1. Feedback bit is input XOR'd with the LSB
        feedback = data_in ^ crc_out[0]; 

        // 2. The register shifts RIGHT, with feedback XOR'd at the taps.
        // Polynomial: x^24 + x^10 + x^9 + x^6 + x^4 + x^3 + x + 1
        // Taps: 24, 10, 9, 6, 4, 3, 1, 0
        
        crc_next[0]  = crc_out[1]  ^ feedback; // Tap x^1
        crc_next[1]  = crc_out[2];
        crc_next[2]  = crc_out[3]  ^ feedback; // Tap x^3
        crc_next[3]  = crc_out[4]  ^ feedback; // Tap x^4
        crc_next[4]  = crc_out[5];
        crc_next[5]  = crc_out[6]  ^ feedback; // Tap x^6
        crc_next[6]  = crc_out[7];
        crc_next[7]  = crc_out[8];
        crc_next[8]  = crc_out[9]  ^ feedback; // Tap x^9
        crc_next[9]  = crc_out[10] ^ feedback; // Tap x^10
        crc_next[10] = crc_out[11];
        crc_next[11] = crc_out[12];
        crc_next[12] = crc_out[13];
        crc_next[13] = crc_out[14];
        crc_next[14] = crc_out[15];
        crc_next[15] = crc_out[16];
        crc_next[16] = crc_out[17];
        crc_next[17] = crc_out[18];
        crc_next[18] = crc_out[19];
        crc_next[19] = crc_out[20];
        crc_next[20] = crc_out[21];
        crc_next[21] = crc_out[22];
        crc_next[22] = crc_out[23];
        crc_next[23] = feedback;             // Tap x^24
    end
    // --- Process 2: Sequential Logic (Memory) ---
    always @(posedge clk or negedge rst_n) begin
        if (!rst_n) begin
            crc_out <= CRC_INIT;
        end else if (enable) begin
            crc_out <= crc_next;
        end
    end

endmodule

Testbenches/crc24_gen_tb.v
`timescale 1ns / 1ps

module tb_crc24_gen;

    // --- Internal Signals ---
    reg        clk;
    reg        rst_n;
    reg        enable;
    reg        data_in;
    wire [23:0] crc_out;

    // --- Instantiate the Device Under Test (DUT) ---
    crc24_gen uut (
        .clk(clk),
        .rst_n(rst_n),
        .enable(enable),
        .data_in(data_in),
        .crc_out(crc_out)
    );

    // --- Clock Generator ---
    parameter CLK_PERIOD = 50;
    always begin
        clk = 0; #(CLK_PERIOD / 2);
        clk = 1; #(CLK_PERIOD / 2);
    end

    // --- Helper Task (defined at module level) ---
    task send_bit;
        input bit_to_send;
        begin
            @(negedge clk);
            enable = 1;
            data_in = bit_to_send;
            @(posedge clk);
            #1;
            enable = 0;
        end
    endtask

    // --- Test Sequence ---
    initial begin
        $dumpfile("waveform.vcd");
        $dumpvars(0, tb_crc24_gen);

        $display("Starting simulation...");
        rst_n = 0;
        enable = 0;
        data_in = 0;
        #(CLK_PERIOD * 2);
        
        rst_n = 1;
        #(CLK_PERIOD);
        $display("Reset released. CRC should be 555555. Is: %h", crc_out);

        #(CLK_PERIOD * 2);

        // 4. Send 8-bit PDU: 8'hAB = 10101011
        // **Must be sent LSB-first: 11010101**
        $display("Sending 8-bit PDU 8'hAB (LSB-first: 11010101)");

        // 5. Send all 8 bits (LSB-first)
        send_bit(1); // Bit 0
        send_bit(1); // Bit 1
        send_bit(0); // Bit 2
        send_bit(1); // Bit 3
        send_bit(0); // Bit 4
        send_bit(1); // Bit 5
        send_bit(0); // Bit 6
        send_bit(1); // Bit 7 (MSB)
        
        @(negedge clk);
        enable = 0;
        data_in = 0;
        
        #(CLK_PERIOD * 2);
        
        // 6. Check Final Result
        // The correct LSB-first result for 8'hAB is 9902f7
        $display("PDU sent. Final CRC: %h (Expected: fa577e)", crc_out);

        // 7. Finish simulation
        $display("Simulation complete.");
        $finish;
    end

endmodule

Waveforms/waveform.vcd
$date
	Sun Oct 26 20:33:52 2025
$end
$version
	Icarus Verilog
$end
$timescale
	1ps
$end
$scope module tb_crc24_gen $end
$var wire 24 ! crc_out [23:0] $end
$var parameter 32 " CLK_PERIOD $end
$var reg 1 # clk $end
$var reg 1 $ data_in $end
$var reg 1 % enable $end
$var reg 1 & rst_n $end
$scope module uut $end
$var wire 1 # clk $end
$var wire 1 $ data_in $end
$var wire 1 % enable $end
$var wire 1 & rst_n $end
$var parameter 24 ' CRC_INIT $end
$var reg 24 ( crc_next [23:0] $end
$var reg 24 ) crc_out [23:0] $end
$var reg 1 * feedback $end
$upscope $end
$scope task send_bit $end
$var reg 1 + bit_to_send $end
$upscope $end
$upscope $end
$enddefinitions $end
$comment Show the parameter values. $end
$dumpall
b10101010101010101010101 '
b110010 "
$end
#0
$dumpvars
x+
1*
b10101010101010101010101 )
b101010101010100110000111 (
0&
0%
0$
0#
b10101010101010101010101 !
$end
#25000
1#
#50000
0#
#75000
1#
#100000
0#
1&
#125000
1#
#150000
0#
#175000
1#
#200000
0#
#225000
1#
#250000
b1010101010101010101010 (
0*
1$
1%
0#
1+
#275000
b100101010101011001111000 (
1*
b1010101010101010101010 !
b1010101010101010101010 )
1#
#276000
0%
#300000
1%
0#
#325000
b110010101010100000010001 (
b100101010101011001111000 !
b100101010101011001111000 )
1#
#326000
0+
0%
#350000
b10010101010101100111100 (
0*
0$
1%
0#
#375000
b1001010101010110011110 (
b10010101010101100111100 !
b10010101010101100111100 )
1#
#376000
1+
0%
#400000
b101001010101011010110011 (
1*
1$
1%
0#
#425000
b10100101010101101011001 (
0*
b101001010101011010110011 !
b101001010101011010110011 )
1#
#426000
0+
0%
#450000
b110100101010100001110100 (
1*
0$
1%
0#
#475000
b11010010101010000111010 (
0*
b110100101010100001110100 !
b110100101010100001110100 )
1#
#476000
1+
0%
#500000
b111010010101011100010111 (
1*
1$
1%
0#
#525000
b11101001010101110001011 (
0*
b111010010101011100010111 !
b111010010101011100010111 )
1#
#526000
0+
0%
#550000
b111101001010100010100110 (
1*
0$
1%
0#
#575000
b11110100101010001010011 (
0*
b111101001010100010100110 !
b111101001010100010100110 )
1#
#576000
1+
0%
#600000
b111110100101011101111110 (
1*
1$
1%
0#
#625000
b111111010010100010010010 (
b111110100101011101111110 !
b111110100101011101111110 )
1#
#626000
0%
#650000
b11111010010101110111111 (
0*
0$
0#
