Verilog_files/gfsk_modulator.v
/**
 * @module gfsk_mod
 * @brief Parameterized GFSK Modulator
 * @details Change the parameters at the top to scale the entire design.
 */
module gfsk_modulator #(
    parameter CLK_FREQ  = 400_000_000, // Internal high-speed clock rate
    parameter DATA_RATE = 20_000_000,  // Data rate (matches your sys_clk)
    parameter CARRIER   = 100_000_000, // Target carrier frequency
    parameter DEVIATION = 10_000_000   // Frequency shift for 0 vs 1
)(
    input  wire clk,         // High-speed clock from PLL
    input  wire rst_n,
    input  wire data_in,     // Data arrives at DATA_RATE speed
    output reg  modulated_out
);

    // --- Automatic Math (Computed at Synthesis) ---
    // SPS: Samples Per Symbol (e.g., 400MHz / 20Mbps = 20)
    localparam SPS = CLK_FREQ / DATA_RATE; 
    
    // NCO Tuning Words: (Target_Freq * 2^8) / CLK_FREQ
    localparam [7:0] M_CENTER = (CARRIER * 256) / CLK_FREQ;
    localparam [7:0] M_DEV    = (DEVIATION * 256) / CLK_FREQ;

    // --- Internal Registers ---
    reg [7:0] phase_acc;    // 8-bit Phase Accumulator
    reg [7:0] sample_cnt;   // Tracks samples per bit (0 to SPS-1)
    reg [2:0] shift_reg;    // History for Gaussian smoothing
    reg [7:0] m_current;    // Instantaneous frequency step

    // --- Gaussian Smoothing Logic ---
    // Divides the SPS window into 4 quadrants to ramp the frequency
    always @(*) begin
        case (shift_reg)
            3'b001: begin // Rising Transition
                if      (sample_cnt < (SPS/4))   m_current = M_CENTER - (M_DEV/2);
                else if (sample_cnt < (SPS/2))   m_current = M_CENTER;
                else if (sample_cnt < (3*SPS/4)) m_current = M_CENTER + (M_DEV/2);
                else                             m_current = M_CENTER + M_DEV;
            end
            3'b110: begin // Falling Transition
                if      (sample_cnt < (SPS/4))   m_current = M_CENTER + (M_DEV/2);
                else if (sample_cnt < (SPS/2))   m_current = M_CENTER;
                else if (sample_cnt < (3*SPS/4)) m_current = M_CENTER - (M_DEV/2);
                else                             m_current = M_CENTER - M_DEV;
            end
            3'b111:  m_current = M_CENTER + M_DEV; // Logic 1
            3'b000:  m_current = M_CENTER - M_DEV; // Logic 0
            default: m_current = M_CENTER;
        endcase
    end

    // --- Sequential Logic ---
    always @(posedge clk or negedge rst_n) begin
        if (!rst_n) begin
            phase_acc     <= 8'h00;
            sample_cnt    <= 8'h00;
            shift_reg     <= 3'b000;
            modulated_out <= 1'b0;
        end else begin
            // 1. Bit Timing
            if (sample_cnt >= (SPS - 1)) begin
                sample_cnt  <= 8'h00;
                shift_reg   <= {shift_reg[1:0], data_in};
            end else begin
                sample_cnt  <= sample_cnt + 8'd1;
            end

            // 2. NCO Phase Accumulation
            phase_acc <= phase_acc + m_current;

            // 3. Bitstream Output
            modulated_out <= phase_acc[7];
        end
    end
endmodule

Verilog_files/clock_gen_pll.v
`timescale 1ns / 1ps

module clock_gen_pll (
    input  wire clk_in,    // 20 MHz Input
    input  wire reset,     // Active High Reset
    output reg  clk_out,   // 400 MHz Output
    output reg  locked     // Status signal
);

    // Initial states
    initial begin
        clk_out = 0;
        locked = 0;
    end

    // PLL Locking Logic
    // In an ASIC, the analog loop takes time to stabilize.
    always @(posedge clk_in or posedge reset) begin
        if (reset) begin
            locked <= 0;
        end else begin
            // Simulate a lock time of 200ns
            #200 locked <= 1;
        end
    end

    // 400 MHz Clock Generation
    // Period = 2.5ns. Half-period = 1.25ns.
    always begin
        #1.25 clk_out = ~clk_out;
    end

endmodule

Verilog_files/tx_modulator_clocks.v
/**
 * @module tx_modulator_chain
 * @brief Wrapper for the transmission chain.
 * @details Change SYS_CLK_FREQ and PLL_MULT to scale everything.
 */
module tx_modulator_clocks #(
    parameter SYS_CLK_FREQ = 20_000_000, // CHANGE THIS to 10_000_000 if needed
    parameter PLL_MULT     = 20,         // Keep this at 20 for 20x SPS
    parameter CARRIER_FREQ = 100_000_000,
    parameter DEV_FREQ     = 10_000_000
)(
    input  wire ext_clk,
    input  wire rst_n,
    input  wire whitened_data_in,
    output wire rf_modulated_out
);

    // This calculates the internal frequency used for logic math
    localparam INT_CLK_FREQ = SYS_CLK_FREQ * PLL_MULT;

    wire clk_fast;
    wire locked;

    // --- PLL Instantiation ---
    // Note: You must ensure your PLL IP multiplier matches PLL_MULT
    clock_gen_pll i_pll (
        .clk_in(ext_clk),
        .clk_out(clk_fast),
        .reset(!rst_n),
        .locked(locked)
    );

    // --- GFSK Modulator Instance ---
    gfsk_modulator #(
        .CLK_FREQ(INT_CLK_FREQ),
        .DATA_RATE(SYS_CLK_FREQ), // Data rate tied to system clock
        .CARRIER(CARRIER_FREQ),
        .DEVIATION(DEV_FREQ)
    ) i_gfsk_modulator (
        .clk(clk_fast),
        .rst_n(rst_n && locked),
        .data_in(whitened_data_in),
        .modulated_out(rf_modulated_out)
    );

endmodule

Verilog_files/data_whitener.v
/**
This is the file that performs Data whitening on the PDU as well as the 24 bit CRC
Data whitening is an important process that helps in randomizing the data for better transmissison
Data whitening is done using LFSR wher the initial sequence is derived from the transmission channel index
*/

module data_whitener(
    clk,
    rst_n,
    lfsr_load,          // <-- Added this critical control signal
    enable,
    channel_index,
    data_in,
    whitened_data_out
);
   
   // --- Port Declarations ---
   input        clk;
   input        rst_n;
   input        lfsr_load;      // Pulse to load the channel value
   input        enable;         // Pulse to advance the LFSR
   input  [5:0] channel_index;
   input        data_in;
   output       whitened_data_out; // This is a 1-bit wire

   // --- Internal Signals ---
   reg  [6:0]    lfsr;           // The 7-bit LFSR register
   wire [6:0]    lfsr_seed;    // The 7-bit seed (from channel_index)
   wire [6:0]    lfsr_next;    // The next combinational value for the LFSR
   wire          lfsr_out_bit; // The LSB of the LFSR, used for whitening

   // --- Combinational Logic (The "Calculator") ---

   // 1. Create the 7-bit seed from the 6-bit channel index

   assign lfsr_seed = {channel_index, 1'b0};

   // 2. Define the LFSR's next-state logic (the polynomial)
   //    Polynomial: x^7 + x^4 + 1
   //    Taps are at lfsr[6] (for x^7) and lfsr[3] (for x^4)
   assign lfsr_next[6] = lfsr[5];
   assign lfsr_next[5] = lfsr[4];
   assign lfsr_next[4] = lfsr[3] ^ lfsr[6]; // Tap for x^4
   assign lfsr_next[3] = lfsr[2];
   assign lfsr_next[2] = lfsr[1];
   assign lfsr_next[1] = lfsr[0];
   assign lfsr_next[0] = lfsr[6];             // Tap for x^7

   // 3. Define the output bit (the LSB)
   assign lfsr_out_bit = lfsr[0];

   // 4. Define the final whitened output
   assign whitened_data_out = data_in ^ lfsr_out_bit;


   // --- Sequential Logic (The "Memory") ---
   // This block controls the LFSR register.
   // Load has priority over enable.
   always @(posedge clk or negedge rst_n) begin
        if (!rst_n) begin
            lfsr <= 7'b1111111; // Reset to a non-zero state
        end 
        else if (lfsr_load) begin
            // Load the LFSR with the channel seed value
            lfsr <= lfsr_seed; 
        end 
        else if (enable) begin
            // Advance the LFSR to the next state
            lfsr <= lfsr_next;
        end
   end

endmodule

Verilog_files/crc24_gen.v
/**
 * @module crc24_gen
 * @brief Implements the BLE 24-bit CRC
 */
module crc24_gen (
    clk,
    rst_n,
    enable,
    data_in,
    crc_out
);

    // --- Port Declarations ---
    input        clk;
    input        rst_n;
    input        enable;
    input        data_in;
    output [23:0] crc_out;

    // --- Internal Signals ---
    reg [23:0] crc_out;
    reg [23:0] crc_next;
    reg        feedback;

    localparam [23:0] CRC_INIT = 24'h555555;

    // --- Process 1: Combinational Logic (Calculator) ---
    // This logic implements the LSB-first CRC calculation.
 always @(*) begin
        
        // 1. Feedback bit is input XOR'd with the LSB
        feedback = data_in ^ crc_out[0]; 

        // 2. The register shifts RIGHT, with feedback XOR'd at the taps.
        // Polynomial: x^24 + x^10 + x^9 + x^6 + x^4 + x^3 + x + 1
        // Taps: 24, 10, 9, 6, 4, 3, 1, 0
        
        crc_next[0]  = crc_out[1]  ^ feedback; // Tap x^1
        crc_next[1]  = crc_out[2];
        crc_next[2]  = crc_out[3]  ^ feedback; // Tap x^3
        crc_next[3]  = crc_out[4]  ^ feedback; // Tap x^4
        crc_next[4]  = crc_out[5];
        crc_next[5]  = crc_out[6]  ^ feedback; // Tap x^6
        crc_next[6]  = crc_out[7];
        crc_next[7]  = crc_out[8];
        crc_next[8]  = crc_out[9]  ^ feedback; // Tap x^9
        crc_next[9]  = crc_out[10] ^ feedback; // Tap x^10
        crc_next[10] = crc_out[11];
        crc_next[11] = crc_out[12];
        crc_next[12] = crc_out[13];
        crc_next[13] = crc_out[14];
        crc_next[14] = crc_out[15];
        crc_next[15] = crc_out[16];
        crc_next[16] = crc_out[17];
        crc_next[17] = crc_out[18];
        crc_next[18] = crc_out[19];
        crc_next[19] = crc_out[20];
        crc_next[20] = crc_out[21];
        crc_next[21] = crc_out[22];
        crc_next[22] = crc_out[23];
        crc_next[23] = feedback;             // Tap x^24
    end
    // --- Process 2: Sequential Logic (Memory) ---
    always @(posedge clk or negedge rst_n) begin
        if (!rst_n) begin
            crc_out <= CRC_INIT;
        end else if (enable) begin
            crc_out <= crc_next;
        end
    end

endmodule

Verilog_files/packet_framer.v
/**
 * @module packet_framer
 * @brief ASIC-ready BLE Packet Framer with Dynamic Length Tracking.
 */
module packet_framer #(
    parameter [31:0] ACCESS_ADDR = 32'h8E89BED6, // Advertising Access Address
    parameter [5:0]  CHANNEL_IDX = 6'd37         // Default Adv Channel
)(
    input  wire        clk,               // 20MHz System Clock
    input  wire        rst_n,
    input  wire        start_tx,          // Pulse to start packet
    input  wire [7:0]  tx_data_in,        // From CPU/DMA
    input  wire        tx_valid_in,       // Data valid handshake
    input  wire [23:0] crc_in,            // From CRC Engine
    
    output reg         tx_ready_out,      // Handshake to CPU
    output reg         irq_tx_done,       // Interrupt: Packet complete
    output reg         crc_enable,        // Enable CRC block
    output reg         whitener_enable,   // Enable Whitener block
    output wire [5:0]  channel_index_out, // For Whitener seed
    output reg         serial_data_out    // To Whitener/Modulator
);

    // --- State Encoding (7 States) ---
    localparam IDLE         = 3'd0,
               PREAMBLE     = 3'd1,
               ADDR         = 3'd2,
               HEADER       = 3'd3,
               PAYLOAD      = 3'd4,
               CRC_SUM      = 3'd5,
               DONE         = 3'd6;

    reg [2:0] state;
    reg [5:0] bit_cnt;       // Counts bits within fields
    reg [7:0] byte_cnt;      // Counts total bytes in PDU
    reg [7:0] packet_length; // Captured from 2nd byte of PDU
    reg [7:0] shift_reg;     // Serialization buffer

    assign channel_index_out = CHANNEL_IDX;

    // --- FSM Logic ---
    always @(posedge clk or negedge rst_n) begin
        if (!rst_n) begin
            state           <= IDLE;
            bit_cnt         <= 0;
            byte_cnt        <= 0;
            packet_length   <= 0;
            tx_ready_out    <= 0;
            irq_tx_done     <= 0;
            crc_enable      <= 0;
            whitener_enable <= 0;
            serial_data_out <= 0;
            shift_reg       <= 0;
        end else begin
            case (state)
                
                // 1. IDLE: Wait for start command
                IDLE: begin
                    irq_tx_done <= 0;
                    if (start_tx) begin
                        state   <= PREAMBLE;
                        bit_cnt <= 0;
                    end
                end

                // 2. PREAMBLE: Send fixed 8'hAA (LSB first: 01010101)
                PREAMBLE: begin
                    serial_data_out <= bit_cnt[0]; 
                    if (bit_cnt == 7) begin
                        state   <= ADDR;
                        bit_cnt <= 0;
                    end else bit_cnt <= bit_cnt + 1'b1;
                end

                // 3. ACCESS_ADDR: Send 32-bit address (No Whitening/CRC)
                ADDR: begin
                    serial_data_out <= ACCESS_ADDR[bit_cnt[4:0]];
                    if (bit_cnt == 31) begin
                        state        <= HEADER;
                        bit_cnt      <= 0;
                        tx_ready_out <= 1; // Request first byte of PDU
                    end else bit_cnt <= bit_cnt + 1'b1;
                end

                // 4. HEADER: Send 16-bit PDU Header (Whitening & CRC Start)
                HEADER: begin
                    whitener_enable <= 1;
                    crc_enable      <= 1;

                    if (tx_valid_in && tx_ready_out) begin
                        shift_reg    <= tx_data_in;
                        tx_ready_out <= 0; // Buffer full
                        // Capture length byte (2nd byte of Header)
                        if (byte_cnt == 1) packet_length <= tx_data_in;
                    end

                    serial_data_out <= shift_reg[bit_cnt[2:0]];
                    
                    if (bit_cnt == 7) begin
                        bit_cnt <= 0;
                        tx_ready_out <= 1;
                        if (byte_cnt == 1) begin
                            state <= PAYLOAD;
                            byte_cnt <= 0; // Reset for payload count
                        end else byte_cnt <= byte_cnt + 1'b1;
                    end else bit_cnt <= bit_cnt + 1'b1;
                end

                // 5. PAYLOAD: Send actual data based on captured packet_length
                PAYLOAD: begin
                    if (tx_valid_in && tx_ready_out) begin
                        shift_reg    <= tx_data_in;
                        tx_ready_out <= 0;
                    end

                    serial_data_out <= shift_reg[bit_cnt[2:0]];

                    if (bit_cnt == 7) begin
                        bit_cnt <= 0;
                        tx_ready_out <= 1;
                        // End of payload detection
                        if (byte_cnt == (packet_length - 1)) begin
                            state      <= CRC_SUM;
                            crc_enable <= 0; // Freeze CRC engine
                        end else byte_cnt <= byte_cnt + 1'b1;
                    end else bit_cnt <= bit_cnt + 1'b1;
                end

                // 6. CRC_SUM: Send 24-bit calculated CRC (Whitened)
                CRC_SUM: begin
                    tx_ready_out    <= 0;
                    serial_data_out <= crc_in[bit_cnt[4:0]];
                    if (bit_cnt == 23) begin
                        state           <= DONE;
                        whitener_enable <= 0;
                    end else bit_cnt    <= bit_cnt + 1'b1;
                end

                // 7. DONE: Cleanup and notify CPU
                DONE: begin
                    irq_tx_done     <= 1;
                    serial_data_out <= 0;
                    state           <= IDLE;
                end

                default: state <= IDLE;
            endcase
        end
    end
endmodule

Verilog_files/ble_tx_top.v
/**
 * @module ble_tx_top
 * @brief Top-level integration for the BLE Baseband Transmitter.
 */
module ble_tx_top (
    input  wire        ext_clk,     // 20MHz External Clock
    input  wire        rst_n,
    input  wire        start_tx,    // Pulse to begin packet
    input  wire [7:0]  tx_data_in,  // From CPU/DMA
    input  wire        tx_valid_in, // Data valid handshake
    
    output wire        tx_ready_out, // Handshake to CPU
    output wire        irq_tx_done,  // Interrupt: Packet complete
    output wire        rf_out        // Final GFSK Modulated Signal
);

    // --- Internal Interconnects ---
    wire [5:0]  channel_idx;
    wire [23:0] crc_val;
    wire        framer_serial_out;
    wire        crc_en;
    wire        white_en;
    wire        whitened_stream;

    // 1. Packet Framer (The Conductor)
    packet_framer i_framer (
        .clk(ext_clk),
        .rst_n(rst_n),
        .start_tx(start_tx),
        .tx_data_in(tx_data_in),
        .tx_valid_in(tx_valid_in),
        .crc_in(crc_val),
        .tx_ready_out(tx_ready_out),
        .irq_tx_done(irq_tx_done),
        .crc_enable(crc_en),
        .whitener_enable(white_en),
        .channel_index_out(channel_idx),
        .serial_data_out(framer_serial_out)
    );

    // 2. CRC Engine (The Guard)
    crc24_gen i_crc (
        .clk(ext_clk),
        .rst_n(rst_n),
        .enable(crc_en),
        .data_in(framer_serial_out),
        .crc_out(crc_val)
    );

    // 3. Data Whitener (The Scrambler)
    data_whitener i_whitener (
        .clk(ext_clk),
        .rst_n(rst_n),
        .lfsr_load(start_tx), // Seed LFSR when packet starts
        .enable(white_en),    // Only advance LFSR when in Header/Payload/CRC states
        .channel_index(channel_idx),
        .data_in(framer_serial_out),
        .whitened_data_out(whitened_stream)
    );

    // 4. Modulator Chain (The Radio Interface)
    // Ties the 20MHz whitened stream to the 400MHz GFSK engine
    tx_modulator_clocks i_modulator_chain (
        .ext_clk(ext_clk),
        .rst_n(rst_n),
        .whitened_data_in(whitened_stream),
        .rf_modulated_out(rf_out)
    );

endmodule

Testbenches/ble_tx_system_tb.v
`timescale 1ns / 1ps

/**
 * @module ble_tx_system_tb
 * @brief Comprehensive Testbench for the Full BLE Transmitter Chain.
 */
module ble_tx_system_tb;

    // --- Signals ---
    reg         ext_clk;     // 20MHz System Clock
    reg         rst_n;
    reg         start_tx;
    reg  [7:0]  tx_data_in;
    reg         tx_valid_in;
    
    wire        tx_ready_out;
    wire        irq_tx_done;
    wire        rf_out;      // The 400MHz-sampled GFSK output

    // --- Instantiate the Top-Level System ---
    ble_tx_top uut (
        .ext_clk(ext_clk),
        .rst_n(rst_n),
        .start_tx(start_tx),
        .tx_data_in(tx_data_in),
        .tx_valid_in(tx_valid_in),
        .tx_ready_out(tx_ready_out),
        .irq_tx_done(irq_tx_done),
        .rf_out(rf_out)
    );

    // --- Clock Generation ---
    // 20MHz clock = 50ns period (25ns per toggle)
    initial ext_clk = 0;
    always #25 ext_clk = ~ext_clk;

    // --- Main Test Procedure ---
    initial begin
        // Setup Waveform Dumping
        $dumpfile("ble_system_full.vcd");
        $dumpvars(0, ble_tx_system_tb);

        // 1. System Reset
        $display("[%0t] Starting System Reset...", $time);
        rst_n = 0;
        start_tx = 0;
        tx_data_in = 0;
        tx_valid_in = 0;
        
        #200 rst_n = 1;
        #100; // Wait for PLL Lock simulation

        // 2. Initiate Transmission
        @(posedge ext_clk);
        start_tx = 1;
        @(posedge ext_clk);
        start_tx = 0;
        $display("[%0t] Transmission Triggered.", $time);

        // 3. Feed the BLE Advertisement Packet
        // Standard BLE Header: Type=ADV_IND (0x00), Length=3 (0x03)
        feed_byte(8'h00); // PDU Header Byte 1
        feed_byte(8'h03); // PDU Header Byte 2 (Length field)
        
        // Payload: 0xDE, 0xAD, 0xBE
        feed_byte(8'hDE);
        feed_byte(8'hAD);
        feed_byte(8'hBE);

        // 4. Observe the Chain
        $display("[%0t] All bytes fed. Waiting for CRC and Final Modulation...", $time);
        
        // Wait for the hardware to finish the CRC and trail
        wait(irq_tx_done);
        
        #500; // Final padding to see the waveform end
        $display("[%0t] SUCCESS: Packet Transmission Complete.", $time);
        $finish;
    end

    // --- Task: CPU/DMA Handshake Simulation ---
    task feed_byte(input [7:0] data);
        begin
            // Wait for Framer to be ready for next byte
            while (!tx_ready_out) @(posedge ext_clk);
            
            tx_data_in  = data;
            tx_valid_in = 1;
            
            // Wait for Framer to consume (latch) the byte
            @(posedge ext_clk);
            while (tx_ready_out) @(posedge ext_clk);
            
            tx_valid_in = 0;
            $display("[%0t] System-In: Byte 0x%h accepted.", $time, data);
        end
    endtask

endmodule

ble_system_full.vcd
$date
	Wed Mar  4 17:31:27 2026
$end
$version
	Icarus Verilog
$end
$timescale
	1ps
$end
$scope module ble_tx_system_tb $end
$var wire 1 ! tx_ready_out $end
$var wire 1 " rf_out $end
$var wire 1 # irq_tx_done $end
$var reg 1 $ ext_clk $end
$var reg 1 % rst_n $end
$var reg 1 & start_tx $end
$var reg 8 ' tx_data_in [7:0] $end
$var reg 1 ( tx_valid_in $end
$scope module uut $end
$var wire 6 ) channel_idx [5:0] $end
$var wire 1 $ ext_clk $end
$var wire 1 % rst_n $end
$var wire 1 & start_tx $end
$var wire 8 * tx_data_in [7:0] $end
$var wire 1 ( tx_valid_in $end
$var wire 1 + whitened_stream $end
$var wire 1 , white_en $end
$var wire 1 ! tx_ready_out $end
$var wire 1 " rf_out $end
$var wire 1 # irq_tx_done $end
$var wire 1 - framer_serial_out $end
$var wire 24 . crc_val [23:0] $end
$var wire 1 / crc_en $end
$scope module i_crc $end
$var wire 1 $ clk $end
$var wire 1 % rst_n $end
$var wire 1 / enable $end
$var wire 1 - data_in $end
$var parameter 24 0 CRC_INIT $end
$var reg 24 1 crc_next [23:0] $end
$var reg 24 2 crc_out [23:0] $end
$var reg 1 3 feedback $end
$upscope $end
$scope module i_framer $end
$var wire 6 4 channel_index_out [5:0] $end
$var wire 1 $ clk $end
$var wire 24 5 crc_in [23:0] $end
$var wire 1 % rst_n $end
$var wire 1 & start_tx $end
$var wire 8 6 tx_data_in [7:0] $end
$var wire 1 ( tx_valid_in $end
$var parameter 32 7 ACCESS_ADDR $end
$var parameter 3 8 ADDR $end
$var parameter 6 9 CHANNEL_IDX $end
$var parameter 3 : CRC_SUM $end
$var parameter 3 ; DONE $end
$var parameter 3 < HEADER $end
$var parameter 3 = IDLE $end
$var parameter 3 > PAYLOAD $end
$var parameter 3 ? PREAMBLE $end
$var reg 6 @ bit_cnt [5:0] $end
$var reg 8 A byte_cnt [7:0] $end
$var reg 1 / crc_enable $end
$var reg 1 # irq_tx_done $end
$var reg 8 B packet_length [7:0] $end
$var reg 1 - serial_data_out $end
$var reg 8 C shift_reg [7:0] $end
$var reg 3 D state [2:0] $end
$var reg 1 ! tx_ready_out $end
$var reg 1 , whitener_enable $end
$upscope $end
$scope module i_modulator_chain $end
$var wire 1 $ ext_clk $end
$var wire 1 % rst_n $end
$var wire 1 + whitened_data_in $end
$var wire 1 " rf_modulated_out $end
$var wire 1 E locked $end
$var wire 1 F clk_fast $end
$var parameter 32 G CARRIER_FREQ $end
$var parameter 32 H DEV_FREQ $end
$var parameter 64 I INT_CLK_FREQ $end
$var parameter 32 J PLL_MULT $end
$var parameter 32 K SYS_CLK_FREQ $end
$scope module i_gfsk_modulator $end
$var wire 1 L rst_n $end
$var wire 1 + data_in $end
$var wire 1 F clk $end
$var parameter 32 M CARRIER $end
$var parameter 64 N CLK_FREQ $end
$var parameter 32 O DATA_RATE $end
$var parameter 32 P DEVIATION $end
$var parameter 8 Q M_CENTER $end
$var parameter 8 R M_DEV $end
$var parameter 64 S SPS $end
$var reg 8 T m_current [7:0] $end
$var reg 1 " modulated_out $end
$var reg 8 U phase_acc [7:0] $end
$var reg 8 V sample_cnt [7:0] $end
$var reg 3 W shift_reg [2:0] $end
$upscope $end
$scope module i_pll $end
$var wire 1 $ clk_in $end
$var wire 1 X reset $end
$var reg 1 F clk_out $end
$var reg 1 E locked $end
$upscope $end
$upscope $end
$scope module i_whitener $end
$var wire 6 Y channel_index [5:0] $end
$var wire 1 $ clk $end
$var wire 1 - data_in $end
$var wire 1 , enable $end
$var wire 1 & lfsr_load $end
$var wire 7 Z lfsr_seed [6:0] $end
$var wire 1 % rst_n $end
$var wire 1 + whitened_data_out $end
$var wire 1 [ lfsr_out_bit $end
$var wire 7 \ lfsr_next [6:0] $end
$var reg 7 ] lfsr [6:0] $end
$upscope $end
$upscope $end
$scope task feed_byte $end
$var reg 8 ^ data [7:0] $end
$upscope $end
$upscope $end
$enddefinitions $end
$comment Show the parameter values. $end
$dumpall
b10100 S
b110 R
b1000000 Q
b100110001001011010000000 P
b1001100010010110100000000 O
b10111110101111000010000000000 N
b101111101011110000100000000 M
b1001100010010110100000000 K
b10100 J
b10111110101111000010000000000 I
b100110001001011010000000 H
b101111101011110000100000000 G
b1 ?
b100 >
b0 =
b11 <
b110 ;
b101 :
b100101 9
b10 8
b10001110100010011011111011010110 7
b10101010101010101010101 0
$end
#0
$dumpvars
bx ^
b1111111 ]
b1101111 \
1[
b1001010 Z
b100101 Y
1X
b0 W
b0 V
b0 U
b111010 T
0L
0F
0E
b0 D
b0 C
b0 B
b0 A
b0 @
b0 6
b10101010101010101010101 5
b100101 4
13
b10101010101010101010101 2
b101010101010100110000111 1
0/
b10101010101010101010101 .
0-
0,
1+
b0 *
b100101 )
0(
b0 '
0&
0%
0$
0#
0"
0!
$end
#1250
1F
#2500
0F
#3750
1F
#5000
0F
#6250
1F
#7500
0F
#8750
1F
#10000
0F
#11250
1F
#12500
0F
#13750
1F
#15000
0F
#16250
1F
#17500
0F
#18750
1F
#20000
0F
#21250
1F
#22500
0F
#23750
1F
#25000
0F
1$
#26250
1F
#27500
0F
#28750
1F
#30000
0F
#31250
1F
#32500
0F
#33750
1F
#35000
0F
#36250
1F
#37500
0F
#38750
1F
#40000
0F
#41250
1F
#42500
0F
#43750
1F
#45000
0F
#46250
1F
#47500
0F
#48750
1F
#50000
0F
0$
#51250
1F
#52500
0F
#53750
1F
#55000
0F
#56250
1F
#57500
0F
#58750
1F
#60000
0F
#61250
1F
#62500
0F
#63750
1F
#65000
0F
#66250
1F
#67500
0F
#68750
1F
#70000
0F
#71250
1F
#72500
0F
#73750
1F
#75000
0F
1$
#76250
1F
#77500
0F
#78750
1F
#80000
0F
#81250
1F
#82500
0F
#83750
1F
#85000
0F
#86250
1F
#87500
0F
#88750
1F
#90000
0F
#91250
1F
#92500
0F
#93750
1F
#95000
0F
#96250
1F
#97500
0F
#98750
1F
#100000
0F
0$
#101250
1F
#102500
0F
#103750
1F
#105000
0F
#106250
1F
#107500
0F
#108750
1F
#110000
0F
#111250
1F
#112500
0F
#113750
1F
#115000
0F
#116250
1F
#117500
0F
#118750
1F
#120000
0F
#121250
1F
#122500
0F
#123750
1F
#125000
0F
1$
#126250
1F
#127500
0F
#128750
1F
#130000
0F
#131250
1F
#132500
0F
#133750
1F
#135000
0F
#136250
1F
#137500
0F
#138750
1F
#140000
0F
#141250
1F
#142500
0F
#143750
1F
#145000
0F
#146250
1F
#147500
0F
#148750
1F
#150000
0F
0$
#151250
1F
#152500
0F
#153750
1F
#155000
0F
#156250
1F
#157500
0F
#158750
1F
#160000
0F
#161250
1F
#162500
0F
#163750
1F
#165000
0F
#166250
1F
#167500
0F
#168750
1F
#170000
0F
#171250
1F
#172500
0F
#173750
1F
#175000
0F
1$
#176250
1F
#177500
0F
#178750
1F
#180000
0F
#181250
1F
#182500
0F
#183750
1F
#185000
0F
#186250
1F
#187500
0F
#188750
1F
#190000
0F
#191250
1F
#192500
0F
#193750
1F
#195000
0F
#196250
1F
#197500
0F
#198750
1F
#200000
0F
0$
0X
1%
#201250
1F
#202500
0F
#203750
1F
#205000
0F
#206250
1F
#207500
0F
#208750
1F
#210000
0F
#211250
1F
#212500
0F
#213750
1F
#215000
0F
#216250
1F
#217500
0F
#218750
1F
#220000
0F
#221250
1F
#222500
0F
#223750
1F
#225000
0F
1$
#226250
1F
#227500
0F
#228750
1F
#230000
0F
#231250
1F
#232500
0F
#233750
1F
#235000
0F
#236250
1F
#237500
0F
#238750
1F
#240000
0F
#241250
1F
#242500
0F
#243750
1F
#245000
0F
#246250
1F
#247500
0F
#248750
1F
#250000
0F
0$
#251250
1F
#252500
0F
#253750
1F
#255000
0F
#256250
1F
#257500
0F
#258750
1F
#260000
0F
#261250
1F
#262500
0F
#263750
1F
#265000
0F
#266250
1F
#267500
0F
#268750
1F
#270000
0F
#271250
1F
#272500
0F
#273750
1F
#275000
0F
1$
#276250
1F
#277500
0F
#278750
1F
#280000
0F
#281250
1F
#282500
0F
#283750
1F
#285000
0F
#286250
1F
#287500
0F
#288750
1F
#290000
0F
#291250
1F
#292500
0F
#293750
1F
#295000
0F
#296250
1F
#297500
0F
#298750
1F
#300000
0F
0$
#301250
1F
#302500
0F
#303750
1F
#305000
0F
#306250
1F
#307500
0F
#308750
1F
#310000
0F
#311250
1F
#312500
0F
#313750
1F
#315000
0F
#316250
1F
#317500
0F
#318750
1F
#320000
0F
#321250
1F
#322500
0F
#323750
1F
#325000
0+
b101 \
0[
b1001010 ]
b1 D
1&
0F
1$
#326250
1F
#327500
0F
#328750
1F
#330000
0F
#331250
1F
#332500
0F
#333750
1F
#335000
0F
#336250
1F
#337500
0F
#338750
1F
#340000
0F
#341250
1F
#342500
0F
#343750
1F
#345000
0F
#346250
1F
#347500
0F
#348750
1F
#350000
0F
0$
#351250
1F
#352500
0F
#353750
1F
#355000
0F
#356250
1F
#357500
0F
#358750
1F
#360000
0F
#361250
1F
#362500
0F
#363750
1F
#365000
0F
#366250
1F
#367500
0F
#368750
1F
#370000
0F
#371250
1F
#372500
0F
#373750
1F
#375000
b1 @
b0 ^
0&
0F
1$
#376250
1F
#377500
0F
#378750
1F
#380000
0F
#381250
1F
#382500
0F
#383750
1F
#385000
0F
#386250
1F
#387500
0F
#388750
1F
#390000
0F
#391250
1F
#392500
0F
#393750
1F
#395000
0F
#396250
1F
#397500
0F
#398750
1F
#400000
0F
0$
#401250
1F
#402500
0F
#403750
1F
#405000
0F
#406250
1F
#407500
0F
#408750
1F
#410000
0F
#411250
1F
#412500
0F
#413750
1F
#415000
0F
#416250
1F
#417500
0F
#418750
1F
#420000
0F
#421250
1F
#422500
0F
#423750
1F
#425000
1+
b1010101010101010101010 1
03
1L
b10 @
1-
1E
0F
1$
#426250
b111010 U
b1 V
1F
#427500
0F
#428750
b1110100 U
b10 V
1F
#430000
0F
#431250
b10101110 U
b11 V
1F
#432500
0F
#433750
1"
b11101000 U
b100 V
1F
#435000
0F
#436250
b100010 U
b101 V
1F
#437500
0F
#438750
0"
b1011100 U
b110 V
1F
#440000
0F
#441250
b10010110 U
b111 V
1F
#442500
0F
#443750
1"
b11010000 U
b1000 V
1F
#445000
0F
#446250
b1010 U
b1001 V
1F
#447500
0F
#448750
0"
b1000100 U
b1010 V
1F
#450000
0F
0$
#451250
b1111110 U
b1011 V
1F
#452500
0F
#453750
b10111000 U
b1100 V
1F
#455000
0F
#456250
1"
b11110010 U
b1101 V
1F
#457500
0F
#458750
b101100 U
b1110 V
1F
#460000
0F
#461250
0"
b1100110 U
b1111 V
1F
#462500
0F
#463750
b10100000 U
b10000 V
1F
#465000
0F
#466250
1"
b11011010 U
b10001 V
1F
#467500
0F
#468750
b10100 U
b10010 V
1F
#470000
0F
#471250
0"
b1001110 U
b10011 V
1F
#472500
0F
#473750
b111101 T
b10001000 U
b1 W
b0 V
1F
#475000
0+
b101010101010100110000111 1
13
b11 @
0-
0F
1$
#476250
1"
b11000101 U
b1 V
1F
#477500
0F
#478750
b10 U
b10 V
1F
#480000
0F
#481250
0"
b111111 U
b11 V
1F
#482500
0F
#483750
b1111100 U
b100 V
1F
#485000
0F
#486250
b1000000 T
b10111001 U
b101 V
1F
#487500
0F
#488750
1"
b11111001 U
b110 V
1F
#490000
0F
#491250
b111001 U
b111 V
1F
#492500
0F
#493750
0"
b1111001 U
b1000 V
1F
#495000
0F
#496250
b10111001 U
b1001 V
1F
#497500
0F
#498750
b1000011 T
1"
b11111001 U
b1010 V
1F
#500000
0F
0$
#501250
b111100 U
b1011 V
1F
#502500
0F
#503750
0"
b1111111 U
b1100 V
1F
#505000
0F
#506250
b11000010 U
b1101 V
1F
#507500
0F
