Verilog_files/packet_framer.v
/**
 * @module packet_framer
 * @brief ASIC-ready BLE Packet Framer with Dynamic Length Tracking.
 */
module packet_framer #(
    parameter [31:0] ACCESS_ADDR = 32'h8E89BED6, // Advertising Access Address
    parameter [5:0]  CHANNEL_IDX = 6'd37         // Default Adv Channel
)(
    input  wire        clk,               // 20MHz System Clock
    input  wire        rst_n,
    input  wire        start_tx,          // Pulse to start packet
    input  wire [7:0]  tx_data_in,        // From CPU/DMA
    input  wire        tx_valid_in,       // Data valid handshake
    input  wire [23:0] crc_in,            // From CRC Engine
    
    output reg         tx_ready_out,      // Handshake to CPU
    output reg         irq_tx_done,       // Interrupt: Packet complete
    output reg         crc_enable,        // Enable CRC block
    output reg         whitener_enable,   // Enable Whitener block
    output wire [5:0]  channel_index_out, // For Whitener seed
    output reg         serial_data_out    // To Whitener/Modulator
);

    // --- State Encoding (7 States) ---
    localparam IDLE         = 3'd0,
               PREAMBLE     = 3'd1,
               ADDR         = 3'd2,
               HEADER       = 3'd3,
               PAYLOAD      = 3'd4,
               CRC_SUM      = 3'd5,
               DONE         = 3'd6;

    reg [2:0] state;
    reg [5:0] bit_cnt;       // Counts bits within fields
    reg [7:0] byte_cnt;      // Counts total bytes in PDU
    reg [7:0] packet_length; // Captured from 2nd byte of PDU
    reg [7:0] shift_reg;     // Serialization buffer

    assign channel_index_out = CHANNEL_IDX;

    // --- FSM Logic ---
    always @(posedge clk or negedge rst_n) begin
        if (!rst_n) begin
            state           <= IDLE;
            bit_cnt         <= 0;
            byte_cnt        <= 0;
            packet_length   <= 0;
            tx_ready_out    <= 0;
            irq_tx_done     <= 0;
            crc_enable      <= 0;
            whitener_enable <= 0;
            serial_data_out <= 0;
            shift_reg       <= 0;
        end else begin
            case (state)
                
                // 1. IDLE: Wait for start command
                IDLE: begin
                    irq_tx_done <= 0;
                    if (start_tx) begin
                        state   <= PREAMBLE;
                        bit_cnt <= 0;
                    end
                end

                // 2. PREAMBLE: Send fixed 8'hAA (LSB first: 01010101)
                PREAMBLE: begin
                    serial_data_out <= bit_cnt[0]; 
                    if (bit_cnt == 7) begin
                        state   <= ADDR;
                        bit_cnt <= 0;
                    end else bit_cnt <= bit_cnt + 1'b1;
                end

                // 3. ACCESS_ADDR: Send 32-bit address (No Whitening/CRC)
                ADDR: begin
                    serial_data_out <= ACCESS_ADDR[bit_cnt[4:0]];
                    if (bit_cnt == 31) begin
                        state        <= HEADER;
                        bit_cnt      <= 0;
                        tx_ready_out <= 1; // Request first byte of PDU
                    end else bit_cnt <= bit_cnt + 1'b1;
                end

                // 4. HEADER: Send 16-bit PDU Header (Whitening & CRC Start)
                HEADER: begin
                    whitener_enable <= 1;
                    crc_enable      <= 1;

                    if (tx_valid_in && tx_ready_out) begin
                        shift_reg    <= tx_data_in;
                        tx_ready_out <= 0; // Buffer full
                        // Capture length byte (2nd byte of Header)
                        if (byte_cnt == 1) packet_length <= tx_data_in;
                    end

                    serial_data_out <= shift_reg[bit_cnt[2:0]];
                    
                    if (bit_cnt == 7) begin
                        bit_cnt <= 0;
                        tx_ready_out <= 1;
                        if (byte_cnt == 1) begin
                            state <= PAYLOAD;
                            byte_cnt <= 0; // Reset for payload count
                        end else byte_cnt <= byte_cnt + 1'b1;
                    end else bit_cnt <= bit_cnt + 1'b1;
                end

                // 5. PAYLOAD: Send actual data based on captured packet_length
                PAYLOAD: begin
                    if (tx_valid_in && tx_ready_out) begin
                        shift_reg    <= tx_data_in;
                        tx_ready_out <= 0;
                    end

                    serial_data_out <= shift_reg[bit_cnt[2:0]];

                    if (bit_cnt == 7) begin
                        bit_cnt <= 0;
                        tx_ready_out <= 1;
                        // End of payload detection
                        if (byte_cnt == (packet_length - 1)) begin
                            state      <= CRC_SUM;
                            crc_enable <= 0; // Freeze CRC engine
                        end else byte_cnt <= byte_cnt + 1'b1;
                    end else bit_cnt <= bit_cnt + 1'b1;
                end

                // 6. CRC_SUM: Send 24-bit calculated CRC (Whitened)
                CRC_SUM: begin
                    tx_ready_out    <= 0;
                    serial_data_out <= crc_in[bit_cnt[4:0]];
                    if (bit_cnt == 23) begin
                        state           <= DONE;
                        whitener_enable <= 0;
                    end else bit_cnt    <= bit_cnt + 1'b1;
                end

                // 7. DONE: Cleanup and notify CPU
                DONE: begin
                    irq_tx_done     <= 1;
                    serial_data_out <= 0;
                    state           <= IDLE;
                end

                default: state <= IDLE;
            endcase
        end
    end
endmodule

Testbenches/packet_framer_tb.v
`timescale 1ns / 1ps

module packet_framer_tb;

    // --- Signals ---
    reg        clk;
    reg        rst_n;
    reg        start_tx;
    reg [7:0]  tx_data_in;
    reg        tx_valid_in;
    reg [23:0] crc_in;
    
    wire       tx_ready_out;
    wire       irq_tx_done;
    wire       crc_enable;
    wire       whitener_enable;
    wire [5:0] channel_index_out;
    wire       serial_data_out;

    // --- Instantiate the Framer ---
    packet_framer #(
        .ACCESS_ADDR(32'h8E89BED6)
    ) uut (
        .clk(clk),
        .rst_n(rst_n),
        .start_tx(start_tx),
        .tx_data_in(tx_data_in),
        .tx_valid_in(tx_valid_in),
        .crc_in(crc_in),
        .tx_ready_out(tx_ready_out),
        .irq_tx_done(irq_tx_done),
        .crc_enable(crc_enable),
        .whitener_enable(whitener_enable),
        .channel_index_out(channel_index_out),
        .serial_data_out(serial_data_out)
    );

    // --- Clock Generation (20MHz) ---
    initial clk = 0;
    always #25 clk = ~clk;

    // --- Test Procedure ---
    initial begin
        $dumpfile("framer_test.vcd");
        $dumpvars(0, packet_framer_tb);

        // 1. Initialize
        rst_n = 0;
        start_tx = 0;
        tx_data_in = 0;
        tx_valid_in = 0;
        crc_in = 24'hABCDEF; // Mock CRC value
        
        #100 rst_n = 1;
        #100;

        // 2. Start Transmission
        @(posedge clk);
        start_tx = 1;
        @(posedge clk);
        start_tx = 0;

        // 3. Simulate Host Feeding Data (PDU Header + 3 Bytes Payload)
        // Header Byte 1: Type
        feed_byte(8'h02); 
        // Header Byte 2: Length (3 bytes)
        feed_byte(8'h03); 
        
        // Payload Bytes
        feed_byte(8'hDE);
        feed_byte(8'hAD);
        feed_byte(8'hBE);

        // 4. Wait for Completion
        wait(irq_tx_done);
        #200;
        
        $display("--- Framer Test Complete ---");
        $finish;
    end

    // --- Task: Simulate a CPU feeding a byte with Handshake ---
    task feed_byte(input [7:0] data);
        begin
            // Wait until Framer is ready
            while (!tx_ready_out) @(posedge clk);
            
            // Apply data and valid signal
            tx_data_in = data;
            tx_valid_in = 1;
            
            // Wait for Framer to consume data
            @(posedge clk);
            while (tx_ready_out) @(posedge clk);
            
            tx_valid_in = 0;
            $display("[%0t] CPU Fed Byte: 0x%h", $time, data);
        end
    endtask

endmodule

framer_test.vcd
$date
	Wed Mar  4 09:09:46 2026
$end
$version
	Icarus Verilog
$end
$timescale
	1ps
$end
$scope module packet_framer_tb $end
$var wire 6 ! channel_index_out [5:0] $end
$var wire 1 " whitener_enable $end
$var wire 1 # tx_ready_out $end
$var wire 1 $ serial_data_out $end
$var wire 1 % irq_tx_done $end
$var wire 1 & crc_enable $end
$var reg 1 ' clk $end
$var reg 24 ( crc_in [23:0] $end
$var reg 1 ) rst_n $end
$var reg 1 * start_tx $end
$var reg 8 + tx_data_in [7:0] $end
$var reg 1 , tx_valid_in $end
$scope module uut $end
$var wire 6 - channel_index_out [5:0] $end
$var wire 1 ' clk $end
$var wire 24 . crc_in [23:0] $end
$var wire 1 ) rst_n $end
$var wire 1 * start_tx $end
$var wire 8 / tx_data_in [7:0] $end
$var wire 1 , tx_valid_in $end
$var parameter 32 0 ACCESS_ADDR $end
$var parameter 3 1 ADDR $end
$var parameter 6 2 CHANNEL_IDX $end
$var parameter 3 3 CRC_SUM $end
$var parameter 3 4 DONE $end
$var parameter 3 5 HEADER $end
$var parameter 3 6 IDLE $end
$var parameter 3 7 PAYLOAD $end
$var parameter 3 8 PREAMBLE $end
$var reg 6 9 bit_cnt [5:0] $end
$var reg 8 : byte_cnt [7:0] $end
$var reg 1 & crc_enable $end
$var reg 1 % irq_tx_done $end
$var reg 8 ; packet_length [7:0] $end
$var reg 1 $ serial_data_out $end
$var reg 8 < shift_reg [7:0] $end
$var reg 3 = state [2:0] $end
$var reg 1 # tx_ready_out $end
$var reg 1 " whitener_enable $end
$upscope $end
$scope task feed_byte $end
$var reg 8 > data [7:0] $end
$upscope $end
$upscope $end
$enddefinitions $end
$comment Show the parameter values. $end
$dumpall
b1 8
b100 7
b0 6
b11 5
b110 4
b101 3
b100101 2
b10 1
b10001110100010011011111011010110 0
$end
#0
$dumpvars
bx >
b0 =
b0 <
b0 ;
b0 :
b0 9
b0 /
b101010111100110111101111 .
b100101 -
0,
b0 +
0*
0)
b101010111100110111101111 (
0'
0&
0%
0$
0#
0"
b100101 !
$end
#25000
1'
#50000
0'
#75000
1'
#100000
0'
1)
#125000
1'
#150000
0'
#175000
1'
#200000
0'
#225000
b1 =
1*
1'
#250000
0'
#275000
b1 9
b10 >
0*
1'
#300000
0'
#325000
b10 9
1$
1'
#350000
0'
#375000
b11 9
0$
1'
#400000
0'
#425000
b100 9
1$
1'
#450000
0'
#475000
b101 9
0$
1'
#500000
0'
#525000
b110 9
1$
1'
#550000
0'
#575000
b111 9
0$
1'
#600000
0'
#625000
b0 9
b10 =
1$
1'
#650000
0'
#675000
b1 9
0$
1'
#700000
0'
#725000
b10 9
1$
1'
#750000
0'
#775000
b11 9
1'
#800000
0'
#825000
b100 9
0$
1'
#850000
0'
#875000
b101 9
1$
1'
#900000
0'
#925000
b110 9
0$
1'
#950000
0'
#975000
b111 9
1$
1'
#1000000
0'
#1025000
b1000 9
1'
#1050000
0'
#1075000
b1001 9
0$
1'
#1100000
0'
#1125000
b1010 9
1$
1'
#1150000
0'
#1175000
b1011 9
1'
#1200000
0'
#1225000
b1100 9
1'
#1250000
0'
#1275000
b1101 9
1'
#1300000
0'
#1325000
b1110 9
1'
#1350000
0'
#1375000
b1111 9
0$
1'
#1400000
0'
#1425000
b10000 9
1$
1'
#1450000
0'
#1475000
b10001 9
1'
#1500000
0'
#1525000
b10010 9
0$
1'
#1550000
0'
#1575000
b10011 9
1'
#1600000
0'
#1625000
b10100 9
1$
1'
#1650000
0'
#1675000
b10101 9
0$
1'
#1700000
0'
#1725000
b10110 9
1'
#1750000
0'
#1775000
b10111 9
1'
#1800000
0'
#1825000
b11000 9
1$
1'
#1850000
0'
#1875000
b11001 9
0$
1'
#1900000
0'
#1925000
b11010 9
1$
1'
#1950000
0'
#1975000
b11011 9
1'
#2000000
0'
#2025000
b11100 9
1'
#2050000
0'
#2075000
b11101 9
0$
1'
#2100000
0'
#2125000
b11110 9
1'
#2150000
0'
#2175000
b11111 9
1'
#2200000
0'
#2225000
1#
b0 9
b11 =
1$
1'
#2250000
0'
#2275000
b1 9
0$
0#
b10 <
1&
1"
1,
b10 +
b10 /
1'
#2300000
0'
#2325000
b10 9
1$
b11 >
0,
1'
#2350000
0'
#2375000
b11 9
0$
1'
#2400000
0'
#2425000
b100 9
1'
#2450000
0'
#2475000
b101 9
1'
#2500000
0'
#2525000
b110 9
1'
#2550000
0'
#2575000
b111 9
1'
#2600000
0'
#2625000
b1 :
1#
b0 9
1'
#2650000
0'
#2675000
b1 9
b11 ;
0#
b11 <
1,
b11 +
b11 /
1'
#2700000
0'
#2725000
b10 9
1$
b11011110 >
0,
1'
#2750000
0'
#2775000
b11 9
0$
1'
#2800000
0'
#2825000
b100 9
1'
#2850000
0'
#2875000
b101 9
1'
#2900000
0'
#2925000
b110 9
1'
#2950000
0'
#2975000
b111 9
1'
#3000000
0'
#3025000
b0 :
b100 =
1#
b0 9
1'
#3050000
0'
#3075000
b1 9
1$
0#
b11011110 <
1,
b11011110 +
b11011110 /
1'
#3100000
0'
#3125000
b10 9
b10101101 >
0,
1'
#3150000
0'
#3175000
b11 9
1'
#3200000
0'
#3225000
b100 9
1'
#3250000
0'
#3275000
b101 9
1'
#3300000
0'
#3325000
b110 9
0$
1'
#3350000
0'
#3375000
b111 9
1$
1'
#3400000
0'
#3425000
b1 :
1#
b0 9
1'
#3450000
0'
#3475000
b1 9
0$
0#
b10101101 <
1,
b10101101 +
b10101101 /
1'
#3500000
0'
#3525000
b10 9
b10111110 >
0,
1'
#3550000
0'
#3575000
b11 9
1$
1'
#3600000
0'
#3625000
b100 9
1'
#3650000
0'
#3675000
b101 9
0$
1'
#3700000
0'
#3725000
b110 9
1$
1'
#3750000
0'
#3775000
b111 9
0$
1'
#3800000
0'
#3825000
b10 :
1#
b0 9
1$
1'
#3850000
0'
#3875000
b1 9
0#
b10111110 <
1,
b10111110 +
b10111110 /
1'
#3900000
0'
#3925000
b10 9
0,
1'
#3950000
0'
#3975000
b11 9
1'
#4000000
0'
#4025000
b100 9
1'
#4050000
0'
#4075000
b101 9
1'
#4100000
0'
#4125000
b110 9
1'
#4150000
0'
#4175000
b111 9
0$
1'
#4200000
0'
#4225000
0&
b101 =
1#
b0 9
1$
1'
#4250000
0'
#4275000
b1 9
0#
1'
#4300000
0'
#4325000
b10 9
1'
#4350000
0'
#4375000
b11 9
1'
#4400000
0'
#4425000
b100 9
1'
#4450000
0'
#4475000
b101 9
0$
1'
#4500000
0'
#4525000
b110 9
1$
1'
#4550000
0'
#4575000
b111 9
1'
#4600000
0'
#4625000
b1000 9
1'
#4650000
0'
#4675000
b1001 9
1'
#4700000
0'
#4725000
b1010 9
0$
1'
#4750000
0'
#4775000
b1011 9
1$
1'
#4800000
0'
#4825000
b1100 9
1'
#4850000
0'
#4875000
b1101 9
0$
1'
#4900000
0'
#4925000
b1110 9
1'
#4950000
0'
#4975000
b1111 9
1$
1'
#5000000
0'
#5025000
b10000 9
1'
#5050000
0'
#5075000
b10001 9
1'
#5100000
0'
#5125000
b10010 9
1'
#5150000
0'
#5175000
b10011 9
0$
1'
#5200000
0'
#5225000
b10100 9
1$
1'
#5250000
0'
#5275000
b10101 9
0$
1'
#5300000
0'
#5325000
b10110 9
1$
1'
#5350000
0'
#5375000
b10111 9
0$
1'
#5400000
0'
#5425000
0"
b110 =
1$
1'
#5450000
0'
#5475000
b0 =
0$
1%
1'
#5500000
0'
#5525000
0%
1'
