Verilog_files/data_whitener.v
/**
This is the file that performs Data whitening on the PDU as well as the 24 bit CRC
Data whitening is an important process that helps in randomizing the data for better transmissison
Data whitening is done using LFSR wher the initial sequence is derived from the transmission channel index
*/

module data_whitener(
    clk,
    rst_n,
    lfsr_load,          // <-- Added this critical control signal
    enable,
    channel_index,
    data_in,
    whitened_data_out
);
   
   // --- Port Declarations ---
   input        clk;
   input        rst_n;
   input        lfsr_load;      // Pulse to load the channel value
   input        enable;         // Pulse to advance the LFSR
   input  [5:0] channel_index;
   input        data_in;
   output       whitened_data_out; // This is a 1-bit wire

   // --- Internal Signals ---
   reg  [6:0]    lfsr;           // The 7-bit LFSR register
   wire [6:0]    lfsr_seed;    // The 7-bit seed (from channel_index)
   wire [6:0]    lfsr_next;    // The next combinational value for the LFSR
   wire          lfsr_out_bit; // The LSB of the LFSR, used for whitening

   // --- Combinational Logic (The "Calculator") ---

   // 1. Create the 7-bit seed from the 6-bit channel index

   assign lfsr_seed = {channel_index, 1'b0};

   // 2. Define the LFSR's next-state logic (the polynomial)
   //    Polynomial: x^7 + x^4 + 1
   //    Taps are at lfsr[6] (for x^7) and lfsr[3] (for x^4)
   assign lfsr_next[6] = lfsr[5];
   assign lfsr_next[5] = lfsr[4];
   assign lfsr_next[4] = lfsr[3] ^ lfsr[6]; // Tap for x^4
   assign lfsr_next[3] = lfsr[2];
   assign lfsr_next[2] = lfsr[1];
   assign lfsr_next[1] = lfsr[0];
   assign lfsr_next[0] = lfsr[6];             // Tap for x^7

   // 3. Define the output bit (the LSB)
   assign lfsr_out_bit = lfsr[0];

   // 4. Define the final whitened output
   assign whitened_data_out = data_in ^ lfsr_out_bit;


   // --- Sequential Logic (The "Memory") ---
   // This block controls the LFSR register.
   // Load has priority over enable.
   always @(posedge clk or negedge rst_n) begin
        if (!rst_n) begin
            lfsr <= 7'b1111111; // Reset to a non-zero state
        end 
        else if (lfsr_load) begin
            // Load the LFSR with the channel seed value
            lfsr <= lfsr_seed; 
        end 
        else if (enable) begin
            // Advance the LFSR to the next state
            lfsr <= lfsr_next;
        end
   end

endmodule

Testbenches/data_whitener_tb.v
`timescale 1ns / 1ps

module tb_data_whitener;

    // --- Inputs ---
    reg        clk;
    reg        rst_n;
    reg        lfsr_load;
    reg        enable;
    reg [5:0]  channel_index;
    reg        data_in;

    // --- Outputs ---
    wire       whitened_data_out;

    // --- Instantiate the Unit Under Test (UUT) ---
    data_whitener uut (
        .clk(clk),
        .rst_n(rst_n),
        .lfsr_load(lfsr_load),
        .enable(enable),
        .channel_index(channel_index),
        .data_in(data_in),
        .whitened_data_out(whitened_data_out)
    );

    // --- Clock Generator (20MHz -> 50ns period) ---
    parameter CLK_PERIOD = 50;
    always begin
        clk = 0; #(CLK_PERIOD / 2);
        clk = 1; #(CLK_PERIOD / 2);
    end

    // --- Test Sequence ---
    initial begin
        // 1. Setup Waveform Dump
        $dumpfile("whitener_wave.vcd");
        $dumpvars(0, tb_data_whitener);

        // 2. Initialization & Reset
        $display("Starting Data Whitener Simulation...");
        rst_n = 0;
        lfsr_load = 0;
        enable = 0;
        channel_index = 0;
        data_in = 0;
        #(CLK_PERIOD * 2);
        
        rst_n = 1;
        #(CLK_PERIOD);

        // 3. Load Channel Index 37 (6'b100101)
        // This should result in LFSR being loaded with 7'b1001010
        @(negedge clk);
        channel_index = 6'b100101;
        lfsr_load = 1;
        @(posedge clk);
        #1 lfsr_load = 0;
        $display("Channel 37 loaded. LFSR should be 7'h4A.");

        // 4. Send a stream of 10 Zeros
        // Since data_in is 0, whitened_data_out will exactly match the LFSR sequence
        $display("Sending 10 zeros. Output should be the scrambling sequence:");
        
        repeat (10) begin
            @(negedge clk);
            enable = 1;
            data_in = 1; 
            @(posedge clk);
            #1; // Wait for logic to settle
            $display("Input: %b | Whitened Output: %b | LFSR State: %b", data_in, whitened_data_out, uut.lfsr);
        end

        enable = 0;
        #(CLK_PERIOD * 5);

        $display("Simulation Complete.");
        $finish;
    end

endmodule

whitener_wave.vcd
$date
	Thu Jan 29 12:00:15 2026
$end
$version
	Icarus Verilog
$end
$timescale
	1ps
$end
$scope module tb_data_whitener $end
$var wire 1 ! whitened_data_out $end
$var parameter 32 " CLK_PERIOD $end
$var reg 6 # channel_index [5:0] $end
$var reg 1 $ clk $end
$var reg 1 % data_in $end
$var reg 1 & enable $end
$var reg 1 ' lfsr_load $end
$var reg 1 ( rst_n $end
$scope module uut $end
$var wire 6 ) channel_index [5:0] $end
$var wire 1 $ clk $end
$var wire 1 % data_in $end
$var wire 1 & enable $end
$var wire 1 ' lfsr_load $end
$var wire 1 ( rst_n $end
$var wire 1 ! whitened_data_out $end
$var wire 7 * lfsr_seed [6:0] $end
$var wire 1 + lfsr_out_bit $end
$var wire 7 , lfsr_next [6:0] $end
$var reg 7 - lfsr [6:0] $end
$upscope $end
$upscope $end
$enddefinitions $end
$comment Show the parameter values. $end
$dumpall
b110010 "
$end
#0
$dumpvars
b1111111 -
b1101111 ,
1+
b0 *
b0 )
0(
0'
0&
0%
0$
b0 #
1!
$end
#25000
1$
#50000
0$
#75000
1$
#100000
0$
1(
#125000
1$
#150000
1'
b1001010 *
b100101 #
b100101 )
0$
#175000
0!
b101 ,
0+
b1001010 -
1$
#176000
0'
#200000
1!
1%
1&
0$
#225000
0!
b1010 ,
1+
b101 -
1$
#250000
0$
#275000
1!
b10100 ,
0+
b1010 -
1$
#300000
0$
#325000
b101000 ,
b10100 -
1$
#350000
0$
#375000
b1010000 ,
b101000 -
1$
#400000
0$
#425000
b110001 ,
b1010000 -
1$
#450000
0$
#475000
0!
b1100010 ,
1+
b110001 -
1$
#500000
0$
#525000
1!
b1010101 ,
0+
b1100010 -
1$
#550000
0$
#575000
0!
b111011 ,
1+
b1010101 -
1$
#600000
0$
#625000
b1110110 ,
b111011 -
1$
#650000
0$
#675000
1!
b1111101 ,
0+
b1110110 -
1$
#676000
0&
