Verilog_files/gfsk_modulator.v
/**
 * @module gfsk_mod
 * @brief Parameterized GFSK Modulator
 * @details Change the parameters at the top to scale the entire design.
 */
module gfsk_modulator #(
    parameter CLK_FREQ  = 400_000_000, // Internal high-speed clock rate
    parameter DATA_RATE = 20_000_000,  // Data rate (matches your sys_clk)
    parameter CARRIER   = 100_000_000, // Target carrier frequency
    parameter DEVIATION = 10_000_000   // Frequency shift for 0 vs 1
)(
    input  wire clk,         // High-speed clock from PLL
    input  wire rst_n,
    input  wire data_in,     // Data arrives at DATA_RATE speed
    output reg  modulated_out
);

    // --- Automatic Math (Computed at Synthesis) ---
    // SPS: Samples Per Symbol (e.g., 400MHz / 20Mbps = 20)
    localparam SPS = CLK_FREQ / DATA_RATE; 
    
    // NCO Tuning Words: (Target_Freq * 2^8) / CLK_FREQ
    localparam [7:0] M_CENTER = (CARRIER * 256) / CLK_FREQ;
    localparam [7:0] M_DEV    = (DEVIATION * 256) / CLK_FREQ;

    // --- Internal Registers ---
    reg [7:0] phase_acc;    // 8-bit Phase Accumulator
    reg [7:0] sample_cnt;   // Tracks samples per bit (0 to SPS-1)
    reg [2:0] shift_reg;    // History for Gaussian smoothing
    reg [7:0] m_current;    // Instantaneous frequency step

    // --- Gaussian Smoothing Logic ---
    // Divides the SPS window into 4 quadrants to ramp the frequency
    always @(*) begin
        case (shift_reg)
            3'b001: begin // Rising Transition
                if      (sample_cnt < (SPS/4))   m_current = M_CENTER - (M_DEV/2);
                else if (sample_cnt < (SPS/2))   m_current = M_CENTER;
                else if (sample_cnt < (3*SPS/4)) m_current = M_CENTER + (M_DEV/2);
                else                             m_current = M_CENTER + M_DEV;
            end
            3'b110: begin // Falling Transition
                if      (sample_cnt < (SPS/4))   m_current = M_CENTER + (M_DEV/2);
                else if (sample_cnt < (SPS/2))   m_current = M_CENTER;
                else if (sample_cnt < (3*SPS/4)) m_current = M_CENTER - (M_DEV/2);
                else                             m_current = M_CENTER - M_DEV;
            end
            3'b111:  m_current = M_CENTER + M_DEV; // Logic 1
            3'b000:  m_current = M_CENTER - M_DEV; // Logic 0
            default: m_current = M_CENTER;
        endcase
    end

    // --- Sequential Logic ---
    always @(posedge clk or negedge rst_n) begin
        if (!rst_n) begin
            phase_acc     <= 8'h00;
            sample_cnt    <= 8'h00;
            shift_reg     <= 3'b000;
            modulated_out <= 1'b0;
        end else begin
            // 1. Bit Timing
            if (sample_cnt >= (SPS - 1)) begin
                sample_cnt  <= 8'h00;
                shift_reg   <= {shift_reg[1:0], data_in};
            end else begin
                sample_cnt  <= sample_cnt + 8'd1;
            end

            // 2. NCO Phase Accumulation
            phase_acc <= phase_acc + m_current;

            // 3. Bitstream Output
            modulated_out <= phase_acc[7];
        end
    end
endmodule

Verilog_files/clock_gen_pll.v
`timescale 1ns / 1ps

module clock_gen_pll (
    input  wire clk_in,    // 20 MHz Input
    input  wire reset,     // Active High Reset
    output reg  clk_out,   // 400 MHz Output
    output reg  locked     // Status signal
);

    // Initial states
    initial begin
        clk_out = 0;
        locked = 0;
    end

    // PLL Locking Logic
    // In an ASIC, the analog loop takes time to stabilize.
    always @(posedge clk_in or posedge reset) begin
        if (reset) begin
            locked <= 0;
        end else begin
            // Simulate a lock time of 200ns
            #200 locked <= 1;
        end
    end

    // 400 MHz Clock Generation
    // Period = 2.5ns. Half-period = 1.25ns.
    always begin
        #1.25 clk_out = ~clk_out;
    end

endmodule

Verilog_files/tx_modulator_clocks.v
/**
 * @module tx_modulator_chain
 * @brief Wrapper for the transmission chain.
 * @details Change SYS_CLK_FREQ and PLL_MULT to scale everything.
 */
module tx_modulator_clocks #(
    parameter SYS_CLK_FREQ = 20_000_000, // CHANGE THIS to 10_000_000 if needed
    parameter PLL_MULT     = 20,         // Keep this at 20 for 20x SPS
    parameter CARRIER_FREQ = 100_000_000,
    parameter DEV_FREQ     = 10_000_000
)(
    input  wire ext_clk,
    input  wire rst_n,
    input  wire whitened_data_in,
    output wire rf_modulated_out
);

    // This calculates the internal frequency used for logic math
    localparam INT_CLK_FREQ = SYS_CLK_FREQ * PLL_MULT;

    wire clk_fast;
    wire locked;

    // --- PLL Instantiation ---
    // Note: You must ensure your PLL IP multiplier matches PLL_MULT
    clock_gen_pll i_pll (
        .clk_in(ext_clk),
        .clk_out(clk_fast),
        .reset(!rst_n),
        .locked(locked)
    );

    // --- GFSK Modulator Instance ---
    gfsk_modulator #(
        .CLK_FREQ(INT_CLK_FREQ),
        .DATA_RATE(SYS_CLK_FREQ), // Data rate tied to system clock
        .CARRIER(CARRIER_FREQ),
        .DEVIATION(DEV_FREQ)
    ) i_gfsk_modulator (
        .clk(clk_fast),
        .rst_n(rst_n && locked),
        .data_in(whitened_data_in),
        .modulated_out(rf_modulated_out)
    );

endmodule

Testbenches/gfsk_modulator_tb.v
`timescale 1ns / 1ps

module gfsk_modulator_tb;

    // --- Simulation Configuration ---
    // Change these to test different "Math" scenarios
    parameter REAL_SYS_FREQ = 20_000_000; 
    parameter REAL_INT_MULT = 20;
    
    // Derived Timing for the Testbench Generator
    parameter SYS_PERIOD = 1000000000 / REAL_SYS_FREQ; // 50ns for 20MHz
    
    // --- Signals ---
    reg  ext_clk;
    reg  rst_n;
    reg  whitened_data_in;
    wire rf_modulated_out;

    // --- Instantiate the Agile Transmission Chain ---
    tx_modulator_clocks #(
        .SYS_CLK_FREQ(REAL_SYS_FREQ),
        .PLL_MULT(REAL_INT_MULT),
        .CARRIER_FREQ(100_000_000),
        .DEV_FREQ(10_000_000)
    ) uut (
        .ext_clk(ext_clk),
        .rst_n(rst_n),
        .whitened_data_in(whitened_data_in),
        .rf_modulated_out(rf_modulated_out)
    );

    // --- Clock Generation ---
    initial ext_clk = 0;
    always #(SYS_PERIOD/2) ext_clk = ~ext_clk;

    // --- Test Sequence ---
    initial begin
        // 1. Setup Waveform Dump
        $dumpfile("gfsk_math_test.vcd");
        $dumpvars(0, gfsk_modulator_tb);
        
        $display("--- Starting GFSK Math Engine Verification ---");
        $display("System Clock: %0d MHz | Target Bitrate: %0d Mbps", REAL_SYS_FREQ/1000000, REAL_SYS_FREQ/1000000);
        
        // 2. Reset Phase
        rst_n = 0;
        whitened_data_in = 0;
        #(SYS_PERIOD * 10);
        rst_n = 1;
        
        // Wait for Behavioral PLL to "Lock"
        wait(uut.locked == 1);
        $display("PLL Locked. Commencing Data Transmission...");

        // 3. Send Test Pattern: 10110
        // We change data on the falling edge of the system clock 
        // to ensure stable setup/hold for the modulator.
        
        send_bit(1);
        send_bit(0);
        send_bit(1);
        send_bit(1);
        send_bit(0);

        // 4. Final Observation Window
        #(SYS_PERIOD * 20);
        $display("--- Simulation Finished ---");
        $finish;
    end

    // --- Task: Send a single bit ---
    task send_bit(input bit_val);
        begin
            @(negedge ext_clk);
            whitened_data_in = bit_val;
            $display("[%0t] Input Bit: %b | Current Frequency Shift: %s", 
                     $time, bit_val, (bit_val ? "Rising/High" : "Falling/Low"));
        end
    endtask

endmodule

miscellaneous/gfsk_math_test.vcd
$date
	Wed Jan 28 19:47:09 2026
$end
$version
	Icarus Verilog
$end
$timescale
	1ps
$end
$scope module gfsk_modulator_tb $end
$var wire 1 ! rf_modulated_out $end
$var parameter 32 " REAL_INT_MULT $end
$var parameter 32 # REAL_SYS_FREQ $end
$var parameter 32 $ SYS_PERIOD $end
$var reg 1 % ext_clk $end
$var reg 1 & rst_n $end
$var reg 1 ' whitened_data_in $end
$scope module uut $end
$var wire 1 % ext_clk $end
$var wire 1 & rst_n $end
$var wire 1 ' whitened_data_in $end
$var wire 1 ! rf_modulated_out $end
$var wire 1 ( locked $end
$var wire 1 ) clk_fast $end
$var parameter 32 * CARRIER_FREQ $end
$var parameter 32 + DEV_FREQ $end
$var parameter 64 , INT_CLK_FREQ $end
$var parameter 32 - PLL_MULT $end
$var parameter 32 . SYS_CLK_FREQ $end
$scope module i_gfsk_modulator $end
$var wire 1 ' data_in $end
$var wire 1 / rst_n $end
$var wire 1 ) clk $end
$var parameter 32 0 CARRIER $end
$var parameter 64 1 CLK_FREQ $end
$var parameter 32 2 DATA_RATE $end
$var parameter 32 3 DEVIATION $end
$var parameter 8 4 M_CENTER $end
$var parameter 8 5 M_DEV $end
$var parameter 64 6 SPS $end
$var reg 8 7 m_current [7:0] $end
$var reg 1 ! modulated_out $end
$var reg 8 8 phase_acc [7:0] $end
$var reg 8 9 sample_cnt [7:0] $end
$var reg 3 : shift_reg [2:0] $end
$upscope $end
$scope module i_pll $end
$var wire 1 % clk_in $end
$var wire 1 ; reset $end
$var reg 1 ) clk_out $end
$var reg 1 ( locked $end
$upscope $end
$upscope $end
$scope task send_bit $end
$var reg 1 < bit_val $end
$upscope $end
$upscope $end
$enddefinitions $end
$comment Show the parameter values. $end
$dumpall
b10100 6
b110 5
b1000000 4
b100110001001011010000000 3
b1001100010010110100000000 2
b10111110101111000010000000000 1
b101111101011110000100000000 0
b1001100010010110100000000 .
b10100 -
b10111110101111000010000000000 ,
b100110001001011010000000 +
b101111101011110000100000000 *
b110010 $
b1001100010010110100000000 #
b10100 "
$end
#0
$dumpvars
x<
1;
b0 :
b0 9
b0 8
b111010 7
0/
0)
0(
0'
0&
0%
0!
$end
#1250
1)
#2500
0)
#3750
1)
#5000
0)
#6250
1)
#7500
0)
#8750
1)
#10000
0)
#11250
1)
#12500
0)
#13750
1)
#15000
0)
#16250
1)
#17500
0)
#18750
1)
#20000
0)
#21250
1)
#22500
0)
#23750
1)
#25000
0)
1%
#26250
1)
#27500
0)
#28750
1)
#30000
0)
#31250
1)
#32500
0)
#33750
1)
#35000
0)
#36250
1)
#37500
0)
#38750
1)
#40000
0)
#41250
1)
#42500
0)
#43750
1)
#45000
0)
#46250
1)
#47500
0)
#48750
1)
#50000
0)
0%
#51250
1)
#52500
0)
#53750
1)
#55000
0)
#56250
1)
#57500
0)
#58750
1)
#60000
0)
#61250
1)
#62500
0)
#63750
1)
#65000
0)
#66250
1)
#67500
0)
#68750
1)
#70000
0)
#71250
1)
#72500
0)
#73750
1)
#75000
0)
1%
#76250
1)
#77500
0)
#78750
1)
#80000
0)
#81250
1)
#82500
0)
#83750
1)
#85000
0)
#86250
1)
#87500
0)
#88750
1)
#90000
0)
#91250
1)
#92500
0)
#93750
1)
#95000
0)
#96250
1)
#97500
0)
#98750
1)
#100000
0)
0%
#101250
1)
#102500
0)
#103750
1)
#105000
0)
#106250
1)
#107500
0)
#108750
1)
#110000
0)
#111250
1)
#112500
0)
#113750
1)
#115000
0)
#116250
1)
#117500
0)
#118750
1)
#120000
0)
#121250
1)
#122500
0)
#123750
1)
#125000
0)
1%
#126250
1)
#127500
0)
#128750
1)
#130000
0)
#131250
1)
#132500
0)
#133750
1)
#135000
0)
#136250
1)
#137500
0)
#138750
1)
#140000
0)
#141250
1)
#142500
0)
#143750
1)
#145000
0)
#146250
1)
#147500
0)
#148750
1)
#150000
0)
0%
#151250
1)
#152500
0)
#153750
1)
#155000
0)
#156250
1)
#157500
0)
#158750
1)
#160000
0)
#161250
1)
#162500
0)
#163750
1)
#165000
0)
#166250
1)
#167500
0)
#168750
1)
#170000
0)
#171250
1)
#172500
0)
#173750
1)
#175000
0)
1%
#176250
1)
#177500
0)
#178750
1)
#180000
0)
#181250
1)
#182500
0)
#183750
1)
#185000
0)
#186250
1)
#187500
0)
#188750
1)
#190000
0)
#191250
1)
#192500
0)
#193750
1)
#195000
0)
#196250
1)
#197500
0)
#198750
1)
#200000
0)
0%
#201250
1)
#202500
0)
#203750
1)
#205000
0)
#206250
1)
#207500
0)
#208750
1)
#210000
0)
#211250
1)
#212500
0)
#213750
1)
#215000
0)
#216250
1)
#217500
0)
#218750
1)
#220000
0)
#221250
1)
#222500
0)
#223750
1)
#225000
0)
1%
#226250
1)
#227500
0)
#228750
1)
#230000
0)
#231250
1)
#232500
0)
#233750
1)
#235000
0)
#236250
1)
#237500
0)
#238750
1)
#240000
0)
#241250
1)
#242500
0)
#243750
1)
#245000
0)
#246250
1)
#247500
0)
#248750
1)
#250000
0)
0%
#251250
1)
#252500
0)
#253750
1)
#255000
0)
#256250
1)
#257500
0)
#258750
1)
#260000
0)
#261250
1)
#262500
0)
#263750
1)
#265000
0)
#266250
1)
#267500
0)
#268750
1)
#270000
0)
#271250
1)
#272500
0)
#273750
1)
#275000
0)
1%
#276250
1)
#277500
0)
#278750
1)
#280000
0)
#281250
1)
#282500
0)
#283750
1)
#285000
0)
#286250
1)
#287500
0)
#288750
1)
#290000
0)
#291250
1)
#292500
0)
#293750
1)
#295000
0)
#296250
1)
#297500
0)
#298750
1)
#300000
0)
0%
#301250
1)
#302500
0)
#303750
1)
#305000
0)
#306250
1)
#307500
0)
#308750
1)
#310000
0)
#311250
1)
#312500
0)
#313750
1)
#315000
0)
#316250
1)
#317500
0)
#318750
1)
#320000
0)
#321250
1)
#322500
0)
#323750
1)
#325000
0)
1%
#326250
1)
#327500
0)
#328750
1)
#330000
0)
#331250
1)
#332500
0)
#333750
1)
#335000
0)
#336250
1)
#337500
0)
#338750
1)
#340000
0)
#341250
1)
#342500
0)
#343750
1)
#345000
0)
#346250
1)
#347500
0)
#348750
1)
#350000
0)
0%
#351250
1)
#352500
0)
#353750
1)
#355000
0)
#356250
1)
#357500
0)
#358750
1)
#360000
0)
#361250
1)
#362500
0)
#363750
1)
#365000
0)
#366250
1)
#367500
0)
#368750
1)
#370000
0)
#371250
1)
#372500
0)
#373750
1)
#375000
0)
1%
#376250
1)
#377500
0)
#378750
1)
#380000
0)
#381250
1)
#382500
0)
#383750
1)
#385000
0)
#386250
1)
#387500
0)
#388750
1)
#390000
0)
#391250
1)
#392500
0)
#393750
1)
#395000
0)
#396250
1)
#397500
0)
#398750
1)
#400000
0)
0%
#401250
1)
#402500
0)
#403750
1)
#405000
0)
#406250
1)
#407500
0)
#408750
1)
#410000
0)
#411250
1)
#412500
0)
#413750
1)
#415000
0)
#416250
1)
#417500
0)
#418750
1)
#420000
0)
#421250
1)
#422500
0)
#423750
1)
#425000
0)
1%
#426250
1)
#427500
0)
#428750
1)
#430000
0)
#431250
1)
#432500
0)
#433750
1)
#435000
0)
#436250
1)
#437500
0)
#438750
1)
#440000
0)
#441250
1)
#442500
0)
#443750
1)
#445000
0)
#446250
1)
#447500
0)
#448750
1)
#450000
0)
0%
#451250
1)
#452500
0)
#453750
1)
#455000
0)
#456250
1)
#457500
0)
#458750
1)
#460000
0)
#461250
1)
#462500
0)
#463750
1)
#465000
0)
#466250
1)
#467500
0)
#468750
1)
#470000
0)
#471250
1)
#472500
0)
#473750
1)
#475000
0)
1%
#476250
1)
#477500
0)
#478750
1)
#480000
0)
#481250
1)
#482500
0)
#483750
1)
#485000
0)
#486250
1)
#487500
0)
#488750
1)
#490000
0)
#491250
1)
#492500
0)
#493750
1)
#495000
0)
#496250
1)
#497500
0)
#498750
1)
#500000
0)
0%
0;
1&
#501250
1)
#502500
0)
#503750
1)
#505000
0)
#506250
1)
#507500
0)
#508750
1)
#510000
0)
#511250
1)
#512500
0)
#513750
1)
#515000
0)
#516250
1)
#517500
0)
#518750
1)
#520000
0)
#521250
1)
#522500
0)
#523750
1)
#525000
0)
1%
#526250
1)
#527500
0)
#528750
1)
#530000
0)
#531250
1)
#532500
0)
#533750
1)
#535000
0)
#536250
1)
#537500
0)
#538750
1)
#540000
0)
#541250
1)
#542500
0)
#543750
1)
#545000
0)
#546250
1)
#547500
0)
#548750
1)
#550000
0)
0%
#551250
1)
#552500
0)
#553750
1)
#555000
0)
#556250
1)
#557500
0)
#558750
1)
#560000
0)
#561250
1)
#562500
0)
#563750
1)
#565000
0)
#566250
1)
#567500
0)
#568750
1)
#570000
0)
#571250
1)
#572500
0)
#573750
1)
#575000
0)
1%
#576250
1)
#577500
0)
#578750
1)
#580000
0)
#581250
1)
#582500
0)
#583750
1)
#585000
0)
#586250
1)
#587500
0)
#588750
1)
#590000
0)
#591250
1)
#592500
0)
#593750
1)
#595000
0)
#596250
1)
#597500
0)
#598750
1)
#600000
0)
0%
#601250
1)
#602500
0)
#603750
1)
#605000
0)
#606250
1)
#607500
0)
#608750
1)
#610000
0)
#611250
1)
#612500
0)
#613750
1)
#615000
0)
#616250
1)
#617500
0)
#618750
1)
#620000
0)
#621250
1)
#622500
0)
#623750
1)
#625000
0)
1%
#626250
1)
#627500
0)
#628750
1)
#630000
0)
#631250
1)
#632500
0)
#633750
1)
#635000
0)
#636250
1)
#637500
0)
#638750
1)
#640000
0)
#641250
1)
#642500
0)
#643750
1)
#645000
0)
#646250
1)
#647500
0)
#648750
1)
#650000
0)
0%
#651250
1)
#652500
0)
#653750
1)
#655000
0)
#656250
1)
#657500
0)
#658750
1)
#660000
0)
#661250
1)
#662500
0)
#663750
1)
#665000
0)
#666250
1)
#667500
0)
#668750
1)
#670000
0)
#671250
1)
#672500
0)
#673750
1)
#675000
0)
1%
#676250
1)
#677500
0)
#678750
1)
#680000
0)
#681250
1)
#682500
0)
#683750
1)
#685000
0)
#686250
1)
#687500
0)
#688750
1)
#690000
0)
#691250
1)
#692500
0)
#693750
1)
#695000
0)
#696250
1)
#697500
0)
#698750
1)
#700000
0)
0%
#701250
1)
#702500
0)
#703750
1)
#705000
0)
#706250
1)
#707500
0)
#708750
1)
#710000
0)
#711250
1)
#712500
0)
#713750
1)
#715000
0)
#716250
1)
#717500
0)
#718750
1)
#720000
0)
#721250
1)
#722500
0)
#723750
1)
#725000
1/
1<
1(
0)
1%
#726250
b111010 8
b1 9
1)
#727500
0)
#728750
b1110100 8
b10 9
1)
#730000
0)
#731250
b10101110 8
b11 9
1)
#732500
0)
#733750
1!
b11101000 8
b100 9
1)
#735000
0)
#736250
b100010 8
b101 9
1)
#737500
0)
#738750
0!
b1011100 8
b110 9
1)
#740000
0)
#741250
b10010110 8
b111 9
1)
#742500
0)
#743750
1!
b11010000 8
b1000 9
1)
#745000
0)
#746250
b1010 8
b1001 9
1)
#747500
0)
#748750
0!
b1000100 8
b1010 9
1)
#750000
0<
1'
0)
0%
#751250
b1111110 8
b1011 9
1)
#752500
0)
#753750
b10111000 8
b1100 9
1)
#755000
0)
#756250
1!
b11110010 8
b1101 9
1)
#757500
0)
#758750
b101100 8
b1110 9
1)
#760000
0)
#761250
0!
b1100110 8
b1111 9
1)
#762500
0)
#763750
b10100000 8
b10000 9
1)
#765000
0)
#766250
1!
b11011010 8
b10001 9
1)
#767500
0)
#768750
b10100 8
b10010 9
1)
#770000
0)
#771250
0!
b1001110 8
b10011 9
1)
#772500
0)
#773750
b111101 7
b10001000 8
b1 :
b0 9
1)
#775000
0)
1%
#776250
1!
b11000101 8
b1 9
1)
#777500
0)
#778750
b10 8
b10 9
1)
#780000
0)
#781250
0!
b111111 8
b11 9
1)
#782500
0)
#783750
b1111100 8
b100 9
1)
#785000
0)
#786250
b1000000 7
b10111001 8
b101 9
1)
#787500
0)
#788750
1!
b11111001 8
b110 9
1)
#790000
0)
#791250
b111001 8
b111 9
1)
#792500
0)
#793750
0!
b1111001 8
b1000 9
1)
#795000
0)
#796250
b10111001 8
b1001 9
1)
#797500
0)
#798750
b1000011 7
1!
b11111001 8
b1010 9
1)
#800000
1<
0'
0)
0%
#801250
b111100 8
b1011 9
1)
#802500
0)
#803750
0!
b1111111 8
b1100 9
1)
#805000
0)
#806250
b11000010 8
b1101 9
1)
#807500
0)
#808750
1!
b101 8
b1110 9
1)
#810000
0)
#811250
b1000110 7
0!
b1001000 8
b1111 9
1)
#812500
0)
#813750
b10001110 8
b10000 9
1)
#815000
0)
#816250
1!
b11010100 8
b10001 9
1)
#817500
0)
#818750
b11010 8
b10010 9
1)
#820000
0)
#821250
0!
b1100000 8
b10011 9
1)
#822500
0)
#823750
b1000000 7
b10100110 8
b10 :
b0 9
1)
#825000
0)
1%
#826250
1!
b11100110 8
b1 9
1)
#827500
0)
#828750
b100110 8
b10 9
1)
#830000
0)
#831250
0!
b1100110 8
b11 9
1)
#832500
0)
#833750
b10100110 8
b100 9
1)
#835000
0)
#836250
1!
b11100110 8
b101 9
1)
#837500
0)
#838750
b100110 8
b110 9
1)
#840000
0)
#841250
0!
b1100110 8
b111 9
1)
#842500
0)
#843750
b10100110 8
b1000 9
1)
#845000
0)
#846250
1!
b11100110 8
b1001 9
1)
#847500
0)
#848750
b100110 8
b1010 9
1)
#850000
1'
0)
0%
#851250
0!
b1100110 8
b1011 9
1)
#852500
0)
#853750
b10100110 8
b1100 9
1)
#855000
0)
#856250
1!
b11100110 8
b1101 9
1)
#857500
0)
#858750
b100110 8
b1110 9
1)
#860000
0)
#861250
0!
b1100110 8
b1111 9
1)
#862500
0)
#863750
b10100110 8
b10000 9
1)
#865000
0)
#866250
1!
b11100110 8
b10001 9
1)
#867500
0)
#868750
b100110 8
b10010 9
1)
#870000
0)
#871250
0!
b1100110 8
b10011 9
1)
#872500
0)
#873750
b10100110 8
b101 :
b0 9
1)
#875000
0)
1%
#876250
1!
b11100110 8
b1 9
1)
#877500
0)
#878750
b100110 8
b10 9
1)
#880000
0)
#881250
0!
b1100110 8
b11 9
1)
#882500
0)
#883750
b10100110 8
b100 9
1)
#885000
0)
#886250
1!
b11100110 8
b101 9
1)
#887500
0)
#888750
b100110 8
b110 9
1)
#890000
0)
#891250
0!
b1100110 8
b111 9
1)
#892500
0)
#893750
b10100110 8
b1000 9
1)
#895000
0)
#896250
1!
b11100110 8
b1001 9
1)
#897500
0)
#898750
b100110 8
b1010 9
1)
#900000
0<
0)
0%
#901250
0!
b1100110 8
b1011 9
1)
#902500
0)
#903750
b10100110 8
b1100 9
1)
#905000
0)
#906250
1!
b11100110 8
b1101 9
1)
#907500
0)
#908750
b100110 8
b1110 9
1)
#910000
0)
#911250
0!
b1100110 8
b1111 9
1)
#912500
0)
#913750
b10100110 8
b10000 9
1)
#915000
0)
#916250
1!
b11100110 8
b10001 9
1)
#917500
0)
#918750
b100110 8
b10010 9
1)
#920000
0)
#921250
0!
b1100110 8
b10011 9
1)
#922500
0)
#923750
b10100110 8
b11 :
b0 9
1)
#925000
0)
1%
#926250
1!
b11100110 8
b1 9
1)
#927500
0)
#928750
b100110 8
b10 9
1)
#930000
0)
#931250
0!
b1100110 8
b11 9
1)
#932500
0)
#933750
b10100110 8
b100 9
1)
#935000
0)
#936250
1!
b11100110 8
b101 9
1)
#937500
0)
#938750
b100110 8
b110 9
1)
#940000
0)
#941250
0!
b1100110 8
b111 9
1)
#942500
0)
#943750
b10100110 8
b1000 9
1)
#945000
0)
#946250
1!
b11100110 8
b1001 9
1)
#947500
0)
#948750
b100110 8
b1010 9
1)
#950000
0'
0)
0%
#951250
0!
b1100110 8
b1011 9
1)
#952500
0)
#953750
b10100110 8
b1100 9
1)
#955000
0)
#956250
1!
b11100110 8
b1101 9
1)
#957500
0)
#958750
b100110 8
b1110 9
1)
#960000
0)
#961250
0!
b1100110 8
b1111 9
1)
#962500
0)
#963750
b10100110 8
b10000 9
1)
#965000
0)
#966250
1!
b11100110 8
b10001 9
1)
#967500
0)
#968750
b100110 8
b10010 9
1)
#970000
0)
#971250
0!
b1100110 8
b10011 9
1)
#972500
0)
#973750
b1000011 7
b10100110 8
b110 :
b0 9
1)
#975000
0)
1%
#976250
1!
b11101001 8
b1 9
1)
#977500
0)
#978750
b101100 8
b10 9
1)
#980000
0)
#981250
0!
b1101111 8
b11 9
1)
#982500
0)
#983750
b10110010 8
b100 9
1)
#985000
0)
#986250
b1000000 7
1!
b11110101 8
b101 9
1)
#987500
0)
#988750
b110101 8
b110 9
1)
#990000
0)
#991250
0!
b1110101 8
b111 9
1)
#992500
0)
#993750
b10110101 8
b1000 9
1)
#995000
0)
#996250
1!
b11110101 8
b1001 9
1)
#997500
0)
#998750
b111101 7
b110101 8
b1010 9
1)
#1000000
0)
0%
#1001250
0!
b1110010 8
b1011 9
1)
#1002500
0)
#1003750
b10101111 8
b1100 9
1)
#1005000
0)
#1006250
1!
b11101100 8
b1101 9
1)
#1007500
0)
#1008750
b101001 8
b1110 9
1)
#1010000
0)
#1011250
b111010 7
0!
b1100110 8
b1111 9
1)
#1012500
0)
#1013750
b10100000 8
b10000 9
1)
#1015000
0)
#1016250
1!
b11011010 8
b10001 9
1)
#1017500
0)
#1018750
b10100 8
b10010 9
1)
#1020000
0)
#1021250
0!
b1001110 8
b10011 9
1)
#1022500
0)
#1023750
b1000000 7
b10001000 8
b100 :
b0 9
1)
#1025000
0)
1%
#1026250
1!
b11001000 8
b1 9
1)
#1027500
0)
#1028750
b1000 8
b10 9
1)
#1030000
0)
#1031250
0!
b1001000 8
b11 9
1)
#1032500
0)
#1033750
b10001000 8
b100 9
1)
#1035000
0)
#1036250
1!
b11001000 8
b101 9
1)
#1037500
0)
#1038750
b1000 8
b110 9
1)
#1040000
0)
#1041250
0!
b1001000 8
b111 9
1)
#1042500
0)
#1043750
b10001000 8
b1000 9
1)
#1045000
0)
#1046250
1!
b11001000 8
b1001 9
1)
#1047500
0)
#1048750
b1000 8
b1010 9
1)
#1050000
0)
0%
#1051250
0!
b1001000 8
b1011 9
1)
#1052500
0)
#1053750
b10001000 8
b1100 9
1)
#1055000
0)
#1056250
1!
b11001000 8
b1101 9
1)
#1057500
0)
#1058750
b1000 8
b1110 9
1)
#1060000
0)
#1061250
0!
b1001000 8
b1111 9
1)
#1062500
0)
#1063750
b10001000 8
b10000 9
1)
#1065000
0)
#1066250
1!
b11001000 8
b10001 9
1)
#1067500
0)
#1068750
b1000 8
b10010 9
1)
#1070000
0)
#1071250
0!
b1001000 8
b10011 9
1)
#1072500
0)
#1073750
b111010 7
b10001000 8
b0 :
b0 9
1)
#1075000
0)
1%
#1076250
1!
b11000010 8
b1 9
1)
#1077500
0)
#1078750
b11111100 8
b10 9
1)
#1080000
0)
#1081250
b110110 8
b11 9
1)
#1082500
0)
#1083750
0!
b1110000 8
b100 9
1)
#1085000
0)
#1086250
b10101010 8
b101 9
1)
#1087500
0)
#1088750
1!
b11100100 8
b110 9
1)
#1090000
0)
#1091250
b11110 8
b111 9
1)
#1092500
0)
#1093750
0!
b1011000 8
b1000 9
1)
#1095000
0)
#1096250
b10010010 8
b1001 9
1)
#1097500
0)
#1098750
1!
b11001100 8
b1010 9
1)
#1100000
0)
0%
#1101250
b110 8
b1011 9
1)
#1102500
0)
#1103750
0!
b1000000 8
b1100 9
1)
#1105000
0)
#1106250
b1111010 8
b1101 9
1)
#1107500
0)
#1108750
b10110100 8
b1110 9
1)
#1110000
0)
#1111250
1!
b11101110 8
b1111 9
1)
#1112500
0)
#1113750
b101000 8
b10000 9
1)
#1115000
0)
#1116250
0!
b1100010 8
b10001 9
1)
#1117500
0)
#1118750
b10011100 8
b10010 9
1)
#1120000
0)
#1121250
1!
b11010110 8
b10011 9
1)
#1122500
0)
#1123750
b10000 8
b0 9
1)
#1125000
0)
1%
#1126250
0!
b1001010 8
b1 9
1)
#1127500
0)
#1128750
b10000100 8
b10 9
1)
#1130000
0)
#1131250
1!
b10111110 8
b11 9
1)
#1132500
0)
#1133750
b11111000 8
b100 9
1)
#1135000
0)
#1136250
b110010 8
b101 9
1)
#1137500
0)
#1138750
0!
b1101100 8
b110 9
1)
#1140000
0)
#1141250
b10100110 8
b111 9
1)
#1142500
0)
#1143750
1!
b11100000 8
b1000 9
1)
#1145000
0)
#1146250
b11010 8
b1001 9
1)
#1147500
0)
#1148750
0!
b1010100 8
b1010 9
1)
#1150000
0)
0%
#1151250
b10001110 8
b1011 9
1)
#1152500
0)
#1153750
1!
b11001000 8
b1100 9
1)
#1155000
0)
#1156250
b10 8
b1101 9
1)
#1157500
0)
#1158750
0!
b111100 8
b1110 9
1)
#1160000
0)
#1161250
b1110110 8
b1111 9
1)
#1162500
0)
#1163750
b10110000 8
b10000 9
1)
#1165000
0)
#1166250
1!
b11101010 8
b10001 9
1)
#1167500
0)
#1168750
b100100 8
b10010 9
1)
#1170000
0)
#1171250
0!
b1011110 8
b10011 9
1)
#1172500
0)
#1173750
b10011000 8
b0 9
1)
#1175000
0)
1%
#1176250
1!
b11010010 8
b1 9
1)
#1177500
0)
#1178750
b1100 8
b10 9
1)
#1180000
0)
#1181250
0!
b1000110 8
b11 9
1)
#1182500
0)
#1183750
b10000000 8
b100 9
1)
#1185000
0)
#1186250
1!
b10111010 8
b101 9
1)
#1187500
0)
#1188750
b11110100 8
b110 9
1)
#1190000
0)
#1191250
b101110 8
b111 9
1)
#1192500
0)
#1193750
0!
b1101000 8
b1000 9
1)
#1195000
0)
#1196250
b10100010 8
b1001 9
1)
#1197500
0)
#1198750
1!
b11011100 8
b1010 9
1)
#1200000
0)
0%
#1201250
b10110 8
b1011 9
1)
#1202500
0)
#1203750
0!
b1010000 8
b1100 9
1)
#1205000
0)
#1206250
b10001010 8
b1101 9
1)
#1207500
0)
#1208750
1!
b11000100 8
b1110 9
1)
#1210000
0)
#1211250
b11111110 8
b1111 9
1)
#1212500
0)
#1213750
b111000 8
b10000 9
1)
#1215000
0)
#1216250
0!
b1110010 8
b10001 9
1)
#1217500
0)
#1218750
b10101100 8
b10010 9
1)
#1220000
0)
#1221250
1!
b11100110 8
b10011 9
1)
#1222500
0)
#1223750
b100000 8
b0 9
1)
#1225000
0)
1%
#1226250
0!
b1011010 8
b1 9
1)
#1227500
0)
#1228750
b10010100 8
b10 9
1)
#1230000
0)
#1231250
1!
b11001110 8
b11 9
1)
#1232500
0)
#1233750
b1000 8
b100 9
1)
#1235000
0)
#1236250
0!
b1000010 8
b101 9
1)
#1237500
0)
#1238750
b1111100 8
b110 9
1)
#1240000
0)
#1241250
b10110110 8
b111 9
1)
#1242500
0)
#1243750
1!
b11110000 8
b1000 9
1)
#1245000
0)
#1246250
b101010 8
b1001 9
1)
#1247500
0)
